Workbook

Sheet Table 2
A2: Travel Itinerary
A3: Quote No. : EB | B3: Client Name: Contact Number: | E3: Travel Date :
A4: Arrival Date : | B4: Guest Name : -- Guest Number : -- | E4: Total Person = | F4: 2
A5: Departure Date : | B5: Transport : MPV 4 Seater Pvt. Car | E5: Nights / Days
A6: PLACE | B6: HOTEL NAME ( Not Booked ) ( With Breakfast ) | E6: PERIOD OF STAY
A7: KUTA | E7: / Nights | F7: 0
A8: GILI TRAWANGAN | E8: / Nights | F8: 0
A9: UBUD | E9: / Nights | F9: 0
A10: NUSA DUA | E10: / Nights | F10: 0
A11: Day -Date ( Approx ) | B11: Pick-Up Time | C11: Pick-Up Point | D11: Tour/Tranasfer program | F11: Meal
A12: 45886 | B12: TBA | C12: Bali Airport | D12: Arrival at Bali Airport - Transfer to Kuta Hotel. | F12: N/A | G12: =VLOOKUP(D12,Sheet1!A:B,2,FALSE) -> 0 | H12: =VLOOKUP(D12,Sheet1!A:C,3,FALSE) -> 10 | I12: =VLOOKUP(F12,Sheet1!E:F,2,FALSE) -> 0
A13: 45887 | B13: TBA | C13: KUTA HOTEL | D13: Arrival at Bali Airport - Transfer to Kuta Hotel. | F13: N/A | G13: =VLOOKUP(D13,Sheet1!A:B,2,FALSE) -> 0 | H13: =VLOOKUP(D13,Sheet1!A:C,3,FALSE) -> 10 | I13: =VLOOKUP(F13,Sheet1!E:F,2,FALSE) -> 0
A14: 45888 | B14: TBA | C14: KUTA HOTEL | D14: Arrival at Bali Airport - Transfer to Kuta Hotel. | F14: N/A | G14: =VLOOKUP(D14,Sheet1!A:B,2,FALSE) -> 0 | H14: =VLOOKUP(D14,Sheet1!A:C,3,FALSE) -> 10 | I14: =VLOOKUP(F14,Sheet1!E:F,2,FALSE) -> 0
A15: 45889 | B15: TBA | C15: KUTA HOTEL | D15: Arrival at Bali Airport - Transfer to Kuta Hotel. | G15: =VLOOKUP(D15,Sheet1!A:B,2,FALSE) -> 0 | H15: =VLOOKUP(D15,Sheet1!A:C,3,FALSE) -> 10 | I15: =VLOOKUP(F15,Sheet1!E:F,2,FALSE) -> #N/A
A16: 45890 | B16: TBA | D16: Arrival at Bali Airport - Transfer to Kuta Hotel. | G16: =VLOOKUP(D16,Sheet1!A:B,2,FALSE) -> 0 | H16: =VLOOKUP(D16,Sheet1!A:C,3,FALSE) -> 10 | I16: =VLOOKUP(F16,Sheet1!E:F,2,FALSE) -> #N/A
A17: 45891 | B17: TBA | D17: Arrival at Bali Airport - Transfer to Kuta Hotel. | G17: =VLOOKUP(D17,Sheet1!A:B,2,FALSE) -> 0 | H17: =VLOOKUP(D17,Sheet1!A:C,3,FALSE) -> 10 | I17: =VLOOKUP(F17,Sheet1!E:F,2,FALSE) -> #N/A
A18: 45892 | B18: TBA | D18: Arrival at Bali Airport - Transfer to Kuta Hotel. | G18: =VLOOKUP(D18,Sheet1!A:B,2,FALSE) -> 0 | H18: =VLOOKUP(D18,Sheet1!A:C,3,FALSE) -> 10 | I18: =VLOOKUP(F18,Sheet1!E:F,2,FALSE) -> #N/A
A19: 45893 | B19: TBA | D19: Arrival at Bali Airport - Transfer to Kuta Hotel. | G19: =VLOOKUP(D19,Sheet1!A:B,2,FALSE) -> 0 | H19: =VLOOKUP(D19,Sheet1!A:C,3,FALSE) -> 10 | I19: =VLOOKUP(F19,Sheet1!E:F,2,FALSE) -> #N/A
A20: Note : Any Airport pickup waiting time 1 Hour from the time of landing of flight. And pickup time from hotel for any international flight 4 hour before departure time. If Any Flight Delay / Early inform us in advance.If any flight early/delay/cancelled due to any reason are not responsible for pickup/drop or missed flight due to pickup/drop. Extra charges applicable in pickup/drop to/from airport without prior information of above.
A21: Breakfast At Hotel. | G21: =SUM(G12:G19) -> 0 | H21: =SUM(H12:H19) -> 80 | I21: =SUM(I12:I19) -> #N/A
A22: Remark 1 : Buy local Sim card at Arrival Airport and send us guest number on our whatsup number for communication. In any airport pickup /drop 1 bag of 20Kg luggage bag per person and 1 hand bag 7 kg per person allowed in car, if more bags extra charges pay by guest. | H22: =(H21/F4) -> 40
A23: Adult Price: USD PP ( Hotel + Transport + Activity sightseen ) | G23: =SUM(G21,H22,I21,) -> #N/A
A24: Only Land Part Price: USD PP ( Transport + Activity sightseen )
A26: Remark:
A27: Price based on twin/triple sharing room per person. We not hold hotel rooms so it subject to availability at the time of booking confirmation from your end.
A28: Prices quoted in USD and subject to change without prior notice.
A29: Please be informed that the quotation does not imply or constitute availability.
A30: In case if the hotel listed is unavailable, other similar class hotel shall be provided.
A31: Indian Meal Optional Cost without transfer – 15 USD per person per meal – 17 USD per person with transfer. (Gujarati/Kathiawadi/Punjabi/South Indian Food served)
A32: Compulsory Gala Dinner will be applied during Christmas Eve and New Year Eve
A33: English Speaking Driver
A34: No (Transport, Activities, Service & Indian Dinner) on 29 March 2025 Nyepi Day.
A36: Price IncludeS:
A37: Transportation with air-conditioned as program PVT.
... A67: INDONESIA IMMIGRATION INFORMATION LINK https://www.indonesia.travel/gb/en/news/new-international-travel-regulations-to-enter-indonesia-as-of-29-november-2021

Sheet Sheet1
A1: Arrival at Bali Airport - Transfer to Kuta Hotel. | C1: 10 | E1: Dinner | F1: 17
A2: Pick up from Kuta Hotel - Bali Airport Drop | C2: 10 | E2: Lunch | F2: 15
A3: Arrival at Bali Airport - Transfer to Ubud Hotel. | C3: 17 | E3: N/A | F3: 0
A4: Pick up from Ubud Hotel - Bali Airport Drop | C4: 17
A5: Arrival at Bali Airport - Transfer to Seminyak Hotel. | C5: 10
A6: Pick up from Seminyak Hotel - Bali Airport Drop | C6: 10
A7: Arrival at Bali Airport - Transfer to Nusa Dua Hotel. | C7: 12
A8: Pick up from Nusa Dua Hotel - Bali Airport Drop | C8: 12
A9: Arrival at Bali Airport - Transfer to Uluwatu Hotel. | C9: 14
A10: Pick up from Uluwatu Hotel - Bali Airport Drop | C10: 14
A11: Arrival at Bali Airport - Transfer to Legien Hotel. | C11: 10
A12: Pick up from Legien Hotel - Bali Airport Drop | C12: 10
A13: Arrival at Bali Airport - Transfer to Jimbaran Hotel. | C13: 10
A14: Pick up from Jimbaran Hotel - Bali Airport Drop | C14: 10
A15: Arrival at Bali Airport - Transfer to Canggu Hotel. | C15: 15
... A35: Inter-hotel Transfer : Uluwatu to Kuta | C35: 13
A37: Full Day Tour - Bintang Beach Club (Banana Boat Ride & Jet Ski with instructor - Parasailing) - Padang Padang Beach -Uluwatu temple - Hotel Drop | B37: 23 | C37: 26
A39: Full Day Tour - Benoa Water Sport Activity (Banana Boat Ride & Jet Ski with instructor - Parasailing) - Uluwatu temple - Candle Light Veg Dinner at Jimbaran Beach ( Rose Stick 2 Pc - Flower Petal Heart Shape Decoration ) - Hotel Drop | B39: 57 | C39: 31
A41: Enjoy a full-day private tour to Bedugul Temple and Tanah Lot for a stunning sunset experience - Hotel Drop | B41: 10 | C41: 27
A43: Full Day Kintamani Volcano Tour with Tegalallanga rice terrace - Ubud Village with coffee plantation, MY bali swing (Single Swing - Fun Adrenalin Swing - Ultimate Swing - Couple swing - Romantic Bed Swing - Family Bed Swing - Chicken Nest - Bird Nest - Sweet Love Nest - Glass Floor - Gate of Heaven) - Hotel Drop | B43: 15 | C43: 28
A45: Enjoy a full-day private tour to Tanah Lot for a stunning sunset experience - MY bali swing (Single Swing - Fun Adrenalin Swing - Ultimate Swing - Couple swing - Romantic Bed Swing - Family Bed Swing - Chicken Nest - Bird Nest - Sweet Love Nest - Glass Floor - Gate of Heaven) - Ubud Hotel Drop | B45: 14 | C45: 32
A47: Full Day Kintamani Tour - (Tegenungan waterfall + coffee plantation + Mount & Lake Batur View + Tegalalang rice terrace + Ubud market) - Hotel Drop | B47: 7 | C47: 28
A49: Full Day Bali Safari Tour - Jungle Hopper - Hotel Drop | B49: 30 | C49: 25
A51: Full Day Kintamani & Ubud Tour with Monkey Forest ( Visit Local Art + Mount & Lake Batur View from Kintamani + coffee plantation + Tegenungan waterfall + Ubud market) - Hotel Drop | B51: 12 | C51: 28
A53: Ubud Hotel - Lempuyang Temple - Tirtha Ganga Temple Tour - Hotel Drop | B53: 13 | C53: 35
A55: Pick up from Hotel - Melasti Beach visit ( watersports by own ) - Uluwatu Sunset temple tour - Kecak dance - Hotel Drop | B55: 13 | C55: 25
A57: Half Day With Inter-hotel Transfer : Kuta to Ubud - Alas Harum swing ( Entry Ticket + Coffee Tour + Access Shop & Restro + Rice Terracee With Selfie Sport + 1 Couple Swing ) - Hotel Drop | B57: 13 | C57: 22
A59: Pick up from Hotel - Enjoy a full-day private tour to Bedugul, Ulun Danu Temple at Breatan lake, Handara Gate - Tanah Lot for a stunning sunset experience - Hotel Drop | B59: 13 | C59: 41
... A109: Fast Boat From Gili Trawanagan Harbour to Bali Mainland (Reach Harbour by own) 1 Hour Before schedule time. (Ticket for return transfer, is provided by Fast Boat Company, during your Onward (Bali to Gili). So Please remember to collect along with onwards ticket. Harbour tax of Gili Trawangan 20.000 IDR Per Person is to be paid directly by the client) - Padang Bai Harbour - Ubud Hotel Drop | B109: 33 | C109: 25

Sheet Table 3
A1: Meeting Point
A3: AIRPORT | B3: INTERNATIONAL ARRIVAL | C3: DOMESTIC ARRIVAL
A4: HO CHI MINH | B4: ARRIVAL PILLAR - 10 GF | C4: ARRIVAL HALL- A1
A5: HANOI | B5: T2 - GATE A & GATE B | C5: T1 - GATE A,B,E
A6: DANANG | B6: GATE 5 | C6: GATE 5
A7: PHU QUOC | B7: Exit Gate | C7: Exit Gate
A9: Terms & Conditions | Advisory Notes
A10: Arrival Notes:
A11: ➢ On the starting day of Tour, Once client local vietnameese number received then WhatsApp group will be created by us, kindly use that for any further communication.
A12: ➢ Guest need to proceed to the Arrival Or Exit Gate & look for airport representative with guest name on Pla card.
A13: ➢ Customer need to wait for 10-15 minutes at the arrival gate once they meet our Airport Representative, Because car park at parking point.
A14: ➢ The maximum waiting period is 90 mins from time of flight landing.
A15: ➢ All Tours and Transfer max waiting period is 10 min SIC basis and 30 Min on PVT Basis.
A16: ➢ Guest need to take care of their belongings while leaving Hotel or Car, We will not be responsible for any belongings.
A18: Hotel Notes:
A19: ➢ Standard Check in Time: 02:00 Pm *Early check in is subject to hotel availability & hotel may charge directly to the guest.
A20: ➢ Standard Check out Time: 11:00 Am Late checkout subject to hotel availability & hotel may charge directly to the guest.
A21: ➢ Hotel may ask for SECURITY DEPOSIT up to 200 USD Or Passport depends on the hotels policy.
... A27: ➢ For Visit to Island, all guest are advised to carry extra pair of clothes, towel and slippers.
