Workbook

Sheet Table 2
A2: Travel Itinerary
A3: Quote No. : | B3: Client Name : Contact Number: | E3: Travel Date : 27 Dec 2025
A4: Arrival Date : 27 Dec 2025 | B4: Guest Name : -- Guest Number : -- | E4: Total Person = 3 | F4: 3
A5: Departure Date : 8 Jan 2026 | B5: Transport : 7 Seater Private Car | E5: 12 Nights / 13 Days
A6: PLACE | B6: 4 STAR HOTEL NAME ( Not Booked ) ( With Breakfast ) | E6: PERIOD OF STAY
A7: HO CHI MINH | B7: Authentic Hanoi Boutique Hotel (Deluxe with window external view) | E7: 27 Dec / Nights | F7: 1 | G7: =VLOOKUP(B7,[1]Sheet4!F:G,2,FALSE) -> 73.333333 | H7: =G7*F7 -> 73.333333 | I7: =H7/2 -> 36.666667
A8: HANOI | B8: Authentic Hanoi Boutique Hotel (Deluxe with window external view) | E8: 28 Dec / Nights | F8: 3 | G8: =VLOOKUP(B8,[1]Sheet4!F:G,2,FALSE) -> 73.333333 | H8: =G8*F8 -> 220 | I8: =H8/2 -> 110
E9: 31 Dec / Nights | F9: 1 | G9: =VLOOKUP(B9,[1]Sheet4!F:G,2,FALSE) -> 0 | H9: =G9*F9 -> 0 | I9: =H9/2 -> 0
E10: 1 January / Nights | F10: 3 | G10: =VLOOKUP(B10,[1]Sheet4!F:G,2,FALSE) -> 0 | H10: =G10*F10 -> 0 | I10: =H10/2 -> 0 | L10: 24947
E11: 4 January / Nights | F11: 3 | G11: =VLOOKUP(B11,[1]Sheet4!F:G,2,FALSE) -> 0 | H11: =G11*F11 -> 0 | I11: =H11/2 -> 0 | L11: 23046
E12: 7 January / Nights | F12: 1 | G12: =VLOOKUP(B12,[1]Sheet4!F:G,2,FALSE) -> 0 | H12: =G12*F12 -> 0 | I12: =H12/2 -> 0
A13: PLACE | B13: 5 STAR HOTEL NAME ( Not Booked ) ( With Breakfast ) | E13: PERIOD OF STAY | J13: =SUM(I8,I10,I11,I12,I7,I9) -> 146.66667
E14: 17 March / Nights | G14: 0 | H14: =G14*F14 -> 0 | I14: =H14/2 -> 0
E15: 20 March / Nights | G15: 0 | H15: =G15*F15 -> 0 | I15: =H15/2 -> 0
E16: 23 March / Nights | G16: 0 | H16: =G16*F16 -> 0 | I16: =H16/2 -> 0
E17: 25 March / Nights | G17: 0 | H17: =G17*F17 -> 0 | I17: =H17/2 -> 0
G18: 0 | H18: =G18*F18 -> 0 | I18: =H18/2 -> 0 | J18: =SUM(I14,I15,I16,I17,I18) -> 0
A19: PLACE | B19: 3 STAR HOTEL NAME ( Not Booked ) ( With Breakfast ) | E19: PERIOD OF STAY | I19: =H19/2 -> 0
B20: Cruise | E20: 15 January / Nights | F20: 2 | G20: =VLOOKUP(B20,[1]Sheet4!M:N,2,FALSE) -> 0 | H20: =G20*F20 -> 0 | I20: =H20/2 -> 0
B21: Cruise | E21: 16 January / Nights | F21: 2 | G21: =VLOOKUP(B21,[1]Sheet4!M:N,2,FALSE) -> 0 | H21: =G21*F21 -> 0 | I21: =H21/2 -> 0
B22: Cruise | E22: 17 January / Nights | F22: 1 | G22: =VLOOKUP(B22,[1]Sheet4!M:N,2,FALSE) -> 0 | H22: =G22*F22 -> 0 | I22: =H22/2 -> 0
B23: Cruise | E23: 18 January / Nights | F23: 1 | G23: =VLOOKUP(B23,[1]Sheet4!M:N,2,FALSE) -> 0 | H23: =G23*F23 -> 0 | I23: =H23/2 -> 0 | J23: =SUM(I20,I21,I22,I23) -> 0
A24: Day -Date ( Approx ) | B24: Pick-Up Time | C24: Pick-Up Point | D24: Guide | E24: Tour/Tranasfer program | F24: Meal | G24: Guide/Person | H24: Tour Program | I24: Meal | J24: Car Rate/Person
E25: --- | F25: N\A | G25: =VLOOKUP(D25,Sheet2!H:I,2,FALSE) -> 0 | H25: =VLOOKUP(E25,Sheet2!A:B,2,FALSE) -> 0 | I25: =VLOOKUP(F25,Sheet2!L:M,2,FALSE) -> 0 | J25: =VLOOKUP(E25,Sheet2!A:C,3,FALSE) -> 0
E26: --- | F26: N\A | G26: =VLOOKUP(D26,Sheet2!H:I,2,FALSE) -> 0 | H26: =VLOOKUP(E26,Sheet2!A:B,2,FALSE) -> 0 | I26: =VLOOKUP(F26,Sheet2!L:M,2,FALSE) -> 0 | J26: =VLOOKUP(E26,Sheet2!A:C,3,FALSE) -> 0
E27: --- | F27: N\A | G27: =VLOOKUP(D27,Sheet2!H:I,2,FALSE) -> 0 | H27: =VLOOKUP(E27,Sheet2!A:B,2,FALSE) -> 0 | I27: =VLOOKUP(F27,Sheet2!L:M,2,FALSE) -> 0 | J27: =VLOOKUP(E27,Sheet2!A:C,3,FALSE) -> 0
E28: --- | F28: N\A | G28: =VLOOKUP(D28,Sheet2!H:I,2,FALSE) -> 0 | H28: 0 | I28: =VLOOKUP(F28,Sheet2!L:M,2,FALSE) -> 0 | J28: 0
E29: --- | F29: N\A | G29: =VLOOKUP(D29,Sheet2!H:I,2,FALSE) -> 0 | H29: 0 | I29: =VLOOKUP(F29,Sheet2!L:M,2,FALSE) -> 0 | J29: 0
E30: --- | F30: N\A | G30: =VLOOKUP(D30,Sheet2!H:I,2,FALSE) -> 0 | H30: =VLOOKUP(E30,Sheet2!A:B,2,FALSE) -> 0 | I30: =VLOOKUP(F30,Sheet2!L:M,2,FALSE) -> 0 | J30: =VLOOKUP(E30,Sheet2!A:C,3,FALSE) -> 0
E31: --- | F31: N\A | G31: =VLOOKUP(D31,Sheet2!H:I,2,FALSE) -> 0 | H31: =VLOOKUP(E31,Sheet2!A:B,2,FALSE) -> 0 | I31: =VLOOKUP(F31,Sheet2!L:M,2,FALSE) -> 0 | J31: =VLOOKUP(E31,Sheet2!A:C,3,FALSE) -> 0
E32: --- | F32: N\A | G32: =VLOOKUP(D32,Sheet2!H:I,2,FALSE) -> 0 | H32: =VLOOKUP(E32,Sheet2!A:B,2,FALSE) -> 0 | I32: =VLOOKUP(F32,Sheet2!L:M,2,FALSE) -> 0 | J32: =VLOOKUP(E32,Sheet2!A:C,3,FALSE) -> 0
E33: --- | F33: N\A | G33: =VLOOKUP(D33,Sheet2!H:I,2,FALSE) -> 0 | H33: =VLOOKUP(E33,Sheet2!A:B,2,FALSE) -> 0 | I33: =VLOOKUP(F33,Sheet2!L:M,2,FALSE) -> 0 | J33: =VLOOKUP(E33,Sheet2!A:C,3,FALSE) -> 0
E34: --- | F34: N\A | G34: =VLOOKUP(D34,Sheet2!H:I,2,FALSE) -> 0 | H34: =VLOOKUP(E34,Sheet2!A:B,2,FALSE) -> 0 | I34: =VLOOKUP(F34,Sheet2!L:M,2,FALSE) -> 0 | J34: =VLOOKUP(E34,Sheet2!A:C,3,FALSE) -> 0
E35: --- | F35: N\A | G35: =VLOOKUP(D35,Sheet2!H:I,2,FALSE) -> 0 | H35: =VLOOKUP(E35,Sheet2!A:B,2,FALSE) -> 0 | I35: =VLOOKUP(F35,Sheet2!L:M,2,FALSE) -> 0 | J35: =VLOOKUP(E35,Sheet2!A:C,3,FALSE) -> 0
E36: --- | F36: N\A | G36: =VLOOKUP(D36,Sheet2!H:I,2,FALSE) -> 0 | H36: =VLOOKUP(E36,Sheet2!A:B,2,FALSE) -> 0 | I36: =VLOOKUP(F36,Sheet2!L:M,2,FALSE) -> 0 | J36: =VLOOKUP(E36,Sheet2!A:C,3,FALSE) -> 0
E37: --- | F37: N\A | G37: =VLOOKUP(D37,Sheet2!H:I,2,FALSE) -> 0 | H37: =VLOOKUP(E37,Sheet2!A:B,2,FALSE) -> 0 | I37: =VLOOKUP(F37,Sheet2!L:M,2,FALSE) -> 0 | J37: =VLOOKUP(E37,Sheet2!A:C,3,FALSE) -> 0
E38: --- | F38: N\A | G38: =VLOOKUP(D38,Sheet2!H:I,2,FALSE) -> 0 | H38: =VLOOKUP(E38,Sheet2!A:B,2,FALSE) -> 0 | I38: =VLOOKUP(F38,Sheet2!L:M,2,FALSE) -> 0 | J38: =VLOOKUP(E38,Sheet2!A:C,3,FALSE) -> 0
E39: --- | F39: N\A | G39: =VLOOKUP(D39,Sheet2!H:I,2,FALSE) -> 0 | H39: =VLOOKUP(E39,Sheet2!A:B,2,FALSE) -> 0 | I39: =VLOOKUP(F39,Sheet2!L:M,2,FALSE) -> 0 | J39: =VLOOKUP(E39,Sheet2!A:C,3,FALSE) -> 0
E40: --- | F40: N\A | G40: =VLOOKUP(D40,Sheet2!H:I,2,FALSE) -> 0 | H40: =VLOOKUP(E40,Sheet2!A:B,2,FALSE) -> 0 | I40: =VLOOKUP(F40,Sheet2!L:M,2,FALSE) -> 0 | J40: =VLOOKUP(E40,Sheet2!A:C,3,FALSE) -> 0
E41: --- | F41: N\A | G41: =VLOOKUP(D41,Sheet2!H:I,2,FALSE) -> 0 | H41: =VLOOKUP(E41,Sheet2!A:B,2,FALSE) -> 0 | I41: =VLOOKUP(F41,Sheet2!L:M,2,FALSE) -> 0 | J41: =VLOOKUP(E41,Sheet2!A:C,3,FALSE) -> 0
... E46: --- | F46: N\A | G46: =VLOOKUP(D46,Sheet2!H:I,2,FALSE) -> 0 | H46: =VLOOKUP(E46,Sheet2!A:B,2,FALSE) -> 0 | I46: =VLOOKUP(F46,Sheet2!L:M,2,FALSE) -> 0 | J46: =VLOOKUP(E46,Sheet2!A:C,3,FALSE) -> 0
A47: Note : Any Airport pickup waiting time 1 Hour from the time of landing of flight. And pickup time from hotel for any international flight 4 hour before departure time, and 3 hour for domestic local vietnam internal flight. If Any Flight Delay / Early inform us in advance.If any flight early/delay/cancelled due to any reason are not responsible for pickup/drop or missed flight due to pickup/drop. Extra charges applicable in pickup/drop to/from airport without prior information of above. | G47: =SUM(G25,G26,G27,G28,G29,G30,G31,G32,G33,G34,G35,G36,G37,G38,G39,G40,G41,G42,G43,G46) -> 0 | H47: =SUM(H25,H26,H27,H28,H29,H30,H31,H32,H33,H34,H35,H36,H37,H38,H39,H40,H41,H42,H43,H46,H45,I44) -> 0 | I47: =SUM(I29+I25+I26+I27+I28+I30+I31+I32+I33+I34+I35+I36+I37+I38+I39+I40+I41+I42+I43+I44+I45+I46) -> 0 | J47: =SUM(J25,J26,J27,J28,J29,J31,J30,J32,J33,J34,J35,J36,J37,J38,J40,J39,J41,J42,J43,J46,J44,J45) -> 0 | O47: =I47/F4 -> 0
G48: =(G47/F4) -> 0 | H48: =SUM(H47,I47) -> 0 | J48: =(J47/F4) -> 0
A49: Remark 1 : Buy local Sim card at Arrival Airport and send us guest number on our whatsup number for communication. In any airport pickup /drop 1 bag of 20Kg luggage bag per person and 1 hand bag 7 kg per person allowed in car, if more bags extra charges pay by guest. | D49: Remark 2: In city tour Temple/Pagoda/Church/Mauseloum - Full cloths compulsory for Gents/ladies/child. Ladies also put Scarf in pocket if needed wear it. Take swimming costume & extra short cloths in theme park and water park tour, Bring Umbrella in your bag during trip. Compulsory Tip : 3 USD per pax per day. | G49: =SUM(G48,H48,J48,J13) -> 146.66667 | I49: =SUM(G48,H48,J48,J18) -> 0 | J49: =SUM(G48,H48,J48,J23) -> 0
A50: Adult Price: USD PP ( Hotel + Food + Transport + Guide + Activity sightseen ) | H50: =SUM(G48,H48,J13,J18,J23,J48) -> 146.66667
A52: Remark:
A53: Price based on twin/triple sharing room per person. We not hold hotel rooms so it subject to availability at the time of booking confirmation from your end.
A54: Prices quoted in USD and subject to change without prior notice.
A55: Please be informed that the quotation does not imply or constitute availability.
A56: In case if the hotel listed is unavailable, other similar class hotel shall be provided.
A57: Compulsory Gala Dinner will be applied during Christmas Eve and New Year Eve
A58: Indian Meal Optional Cost without transfer – 15 USD per person per meal – 17 USD per person with transfer. (Gujarati/Kathiawadi/Punjabi/South Indian Food served)
A59: Airfare is same for children from 2 year-old and adult
A60: TIP is Compulsory for driver & guide is USD 3/pax/day.
A62: Price IncludeS:
A63: Transportation with air-conditioned as program PVT.
A64: Tour arrival and departure airport transfers
... A101: Vietnam Itinerary
A102: =VLOOKUP(E25,[1]Sheet3!A:B,2,FALSE) -> #N/A
A103: =VLOOKUP(E26,[1]Sheet3!A:B,2,FALSE) -> #N/A
A104: =VLOOKUP(E27,[1]Sheet3!A:B,2,FALSE) -> #N/A
A105: =VLOOKUP(E28,[1]Sheet3!A:B,2,FALSE) -> #N/A
A106: =VLOOKUP(E29,[1]Sheet3!A:B,2,FALSE) -> #N/A
A107: =VLOOKUP(E30,[1]Sheet3!A:B,2,FALSE) -> #N/A
A108: =VLOOKUP(E31,[1]Sheet3!A:B,2,FALSE) -> #N/A
A109: =VLOOKUP(E32,[1]Sheet3!A:B,2,FALSE) -> #N/A
A110: =VLOOKUP(E33,[1]Sheet3!A:B,2,FALSE) -> #N/A
A111: =VLOOKUP(E34,[1]Sheet3!A:B,2,FALSE) -> #N/A
A112: =VLOOKUP(E35,[1]Sheet3!A:B,2,FALSE) -> #N/A
A113: =VLOOKUP(E36,[1]Sheet3!A:B,2,FALSE) -> #N/A
... A118: =VLOOKUP(E41,[1]Sheet3!A:B,2,FALSE) -> #N/A

Sheet Sheet2
A1: Hanoi Airport - Hanoi Hotel drop | C1: 19
A2: Hanoi Airport - Hanoi - 4 Hour Hanoi City Tour (HCM Complex + One piller pagoda + Old quarter shopping market + Train Street) - Hanoi Hotel drop | B2: 6 | C2: 54
A3: Hanoi Airport - Hanoi - 4 Hour Hanoi City Tour (HCM Complex + One piller pagoda + Old quarter shopping market + Train Street)- 50 Min Cyclo Tour - Hanoi Hotel Drop | B3: 9 | C3: 54
A4: Hanoi Airport - Hanoi - 4 Hour Hanoi City Tour (HCM Complex + One piller pagoda + Old quarter shopping market + Train Street)- 50 Min Cyclo Tour - Water Puppet Show - Hanoi Hotel Drop | B4: 19 | C4: 54
A5: Hanoi Airport - Hanoi - 4 Hour Hanoi City Tour (HCM Complex + One piller pagoda + Old quarter shopping market + Train Street) - Water Puppet Show - Hanoi Hotel Drop | B5: 14 | C5: 54
A6: Hanoi Hotel - Full Day Hanoi City Tour - Hotel Drop | B6: 6 | C6: 83
A7: Hanoi Hotel - 4 Hours Hanoi City Tour (HCM Complex + One piller pagoda + Old quarter shopping market + Train Street) - Hotel Drop | B7: 6 | C7: 35
A8: Hanoi Airport - 100 KM 2 hours - Ninh Binh Tour - Trang An River boat ride with three caves - Hotel Drop | B8: 13 | C8: 113
A9: Hanoi Airport - 100 KM 2 hours - Ninh Binh Tour (With Lunch)- Trang An River boat ride with three caves - Hotel Drop | B9: 29 | C9: 113
A10: Hanoi Hotel - 100 KM 2 hours - Ninh Binh Tour - Trang An River boat ride with three caves - Hotel Drop | B10: 13 | C10: 94
A11: Hanoi Hotel - 100 KM 2 hours - Ninh Binh Tour (With Lunch) - Trang An River boat ride with three caves - Hotel Drop | B11: 29 | C11: 94 | H11: No | I11: 0 | L11: D | M11: 17
A12: Hanoi Airport - 200 Km 4 hours drive - Halong bay- 11:30 AM need to reach at Halong bay for cruise depart | C12: 182 | H12: Yes | I12: 40 | L12: L,D | M12: 34
A13: Hanoi Hotel - 200 Km 4 hours drive - Halong bay- 11:30 AM need to reach at Halong bay for cruise depart | C13: 182 | H13: 0 | I13: 0 | L13: Local L,Local D | M13: 0
A14: Hanoi Hotel - 200 Km 4 hours drive - Halong bay day cruise - 11:30 AM need to reach at Halong bay for cruise depart - 200 Km 4 hours drive - Hanoi Hotel Drop | B14: 47 | C14: 140 | L14: Local L | M14: 0
A15: Halong Bay - Hanoi 4 hour 200 km Drive - Hanoi Hotel drop | C15: 0 | L15: Local L,D | M15: 17
A16: Halong Bay - Hanoi 4 hour 200 km Drive - Hanoi - 4 hours Hanoi City Tour - Hanoi Hotel drop | B16: 6 | C16: 35 | L16: Local Br,D | M16: 17
A17: Halong Bay - Hanoi 4 hour 200 km Drive - Hanoi Airport drop | C17: 0 | L17: Local Br | M17: 0
A18: Hanoi Airport - 300KM 6 hour Sapa - Sapa Hotel Drop (1 Night) | C18: 338 | L18: L | M18: 17
A19: Hanoi Airport - 300KM 6 hour Sapa - Sapa Hotel Drop (2 Nights) | C19: 338 | L19: Br | M19: 0
A20: Hanoi Airport - 300KM 6 hour Sapa - Sapa Hotel Drop (3 Nights) | C20: 676 | L20: Br,D | M20: 17
A21: Hanoi Hotel - 300KM 6 hour Sapa - Sapa Hotel Drop (1 Night) | C21: 338 | L21: (B,L,D) Limited Indian Food | M21: 0
A22: Hanoi Hotel - 300KM 6 hour Sapa - Sapa Hotel Drop (2 Nights) | C22: 338 | L22: N\A | M22: 0
A23: Hanoi Hotel - 300KM 6 hour Sapa - Sapa Hotel Drop (3 Nights) | C23: 676
A24: Hanoi Airport - 300KM 6 hour Sapa - Moana Sculpture - Sapa Hotel Drop | B24: 8
A25: Hanoi Airport - 300KM 6 hour Sapa - Cat Cat Village Tour - Sapa Hotel Drop | B25: 10
A26: Hanoi Airport - 300KM 6 hour Sapa - Glass Bottom Bridge - Sapa Hotel Drop | B26: 26
A27: Hanoi Hotel - 300KM 6 hour Sapa - Moana Sculpture - Cat Cat Village tour - Sapa Hotel Drop | B27: 18
A28: Sapa Hotel - Moana Sculpture - Cat Cat Village tour - Sapa Hotel Drop | B28: 18
A29: Sapa Hotel - Moana Sculpture - Sapa Hotel Drop | B29: 8
A30: Sapa Hotel - Cat Cat Village tour - Sapa Hotel Drop | B30: 10
A31: Sapa Hotel - Fansipan Mountain - Glass Bottom Bridge - 300km 6 hour drive - Hanoi Hotel drop | B31: 88
A32: Sapa Hotel - Fansipan Mountain - 300km 6 hour drive - Hanoi Hotel drop | B32: 62
A33: Sapa Hotel - Glass Bottom Bridge - 300km 6 hour drive - Hanoi Hotel drop | B33: 26
A34: Sapa Hotel - Fansipan Mountain - Glass Bottom Bridge - Sapa Hotel drop | B34: 88
A35: Sapa Hotel - Fansipan Mountain - Sapa Hotel drop | B35: 62
A36: Sapa Hotel - Glass Bottom Bridge - Sapa Hotel drop | B36: 26
A37: Hanoi Hotel - Hanoi Airport Drop | C37: 0
A38: Sapa Hotel - 300 KM 6 hours Drive - Hanoi Hotel Drop | C38: 15
A39: Sapa Hotel - 300 KM 6 hours Drive - Hanoi - Hanoi Airport Drop | C39: 0
A41: Danang Airport - Danang Hotel Drop | C41: 9
A42: Danang Airport - Danang - Danang City Tour (Dragon Bridge + Pink Church + My Khe Beach + Han Market) - Danang Hotel Drop | B42: 1 | C42: 35
A43: Danang Hotel - Danang City Tour (Dragon Bridge + Pink Church + My Khe Beach + Han Market) - Danang Hotel Drop | B43: 1 | C43: 26
A44: Danang Hotel - Ba Na Hills Tour (2 way cable car + Fantasy park + Golden Bridge + French village ) - Danang hotel | B44: 47 | C44: 36
A45: Danang Hotel - Ba Na Hills Tour (2 way cable car + Fantasy park + Golden Bridge + French village ) (With Lunch) - Danang hotel | B45: 68 | C45: 36
A46: Danang Hotel - Marble Mountain - Coconut Village - Basket Boat Ride - Hoi An Ancient Town - Lantern Boat Ride - Hotel Drop | B46: 16 | C46: 47
A47: Danang Hotel - Marble Mountain - Coconut Village - Basket Boat Ride - Hoi An Ancient Town - Hotel Drop | B47: 13 | C47: 47
A48: Danang Hotel - Marble Mountain - Coconut Village ( Basket Boat Ride By Own ) - Hoi An Ancient Town - Hotel Drop | B48: 9 | C48: 47
A49: Danang Hotel - Marble Mountain - Hoi An Ancient Town - Hotel Drop | B49: 9 | C49: 47
A50: Danang Hotel - Hoi An Ancient Town - Hotel Drop | B50: 6 | C50: 47
A51: Danang Hotel - Coconut Village ( Basket Boat Ride By Own ) - Hoi An Ancient Town - Hotel Drop | B51: 6 | C51: 47
A52: Danang Airport - Marble Mountain - Coconut Village - Basket Boat Ride - Hoi An Ancient Town - Lantern Boat Ride - Hotel Drop | B52: 16 | C52: 56
A53: Danang Airport - Marble Mountain - Coconut Village - Basket Boat Ride - Hoi An Ancient Town - Hotel Drop | B53: 13 | C53: 56
... A58: Danang Hotel - Cham Island Tour - Hotel Drop | B58: 36 | C58: 36
A59: Danang Hotel - Danang Airport Drop | C59: 9
A61: Ho Chi Minh Airport - Ho Chi Minh Hotel Drop | C61: 18
A62: Ho Chi Minh Airport - HCM City Tour (War remnants Museum + Independence +Ben Thanh Market + Presidential Palace + Notre Dame Cathedral) - Ho Chi Minh Hotel Drop | B62: 3 | C62: 75
A63: Ho Chi Minh Airport - HCM city Tour (War remnants Museum + Independence +Ben Thanh Market + Presidential Palace + Notre Dame Cathedral) - Hop on Hop off city tour - Hotel Drop | B63: 16 | C63: 75
A64: Ho Chi Minh Hotel - HCM city Tour (War remnants Museum + Independence +Ben Thanh Market + Presidential Palace + Notre Dame Cathedral) - Hop on Hop off city tour - Hotel Drop | B64: 16 | C64: 57
A65: Ho Chi Minh Hotel - Cu Chi Tunnel Tour - Mekong Delta - Hotel Drop | B65: 12 | C65: 151
A66: Ho Chi Minh Hotel - Cu Chi Tunnel Tour - HCM City Tour (War remnants Museum + Independence +Ben Thanh Market + Presidential Palace + Notre Dame Cathedral) - Hotel Drop | B66: 10 | C66: 114
A67: Ho Chi Minh Airport - Mekong Delta - Ho Chi Minh Hotel drop | B67: 5 | C67: 112
A68: Ho Chi Minh Hotel - Mekong Delta - Hotel drop | B68: 5 | C68: 94
A69: Ho Chi Minh Hotel - Mekong Delta - HCM Airport drop | B69: 5 | C69: 112
A70: Ho Chi Minh Airport - Cu Chi Tunnel Tour - Ho Chi Minh Hotel drop | B70: 7 | C70: 75
A71: HCM Hotel - Cu Chi Tunnel Tour - Hotel drop | B71: 7 | C71: 57
A72: HCM Hotel - Cu Chi Tunnel Tour - HCM Airport drop | B72: 7 | C72: 75
A73: HCM Hotel - HCM Airport Drop | C73: 18
A75: Phu Quoc Airport - Phu Quoc Hotel Drop | C75: 41
A76: Phu Quoc Hotel - Vin Pearl Safari & Vin Wonders - Hotel Drop | B76: 64 | C76: 46
A77: Phu Quoc Hotel - Full Day - 3 Island tour in south by speedboat - Hotel drop | B77: 36 | C77: 73
A78: Phu Quoc Hotel - Full Day - 3 Island tour in south by speedboat - One Way Cable Car - Hotel drop | B78: 65 | C78: 73
A79: Phu Quoc Hotel - Full Day - 4 Island tour in south by speedboat - One Way Cable Car - Aquatopia Water Park - Hotel drop | B79: 65 | C79: 73
A80: Phu Quoc Hotel - Full Day - 4 Island tour in south by speedboat - Hotel drop | B80: 36 | C80: 73
A81: Phu Quoc Hotel - Phu Quoc Airport Drop | C81: 41
A83: Siem Reap Airport - Siem Reap Hotel Drop | C83: 68
A84: Siem Reap Airport - Hotel - Apsara Dance Show - Siem Reap Hotel Drop | C84: 162
A85: Siem Reap Airport - Hotel - Apsara Dance Show - Dinner At Amazon Restaurant - Siem Reap Hotel Drop | B85: 15 | C85: 162
A86: Siem Reap Airport - Hotel - Apsara Dance Show - Dinner At Kanella Restaurant - Siem Reap Hotel Drop | B86: 22 | C86: 162
A87: Siem Reap Hotel - Angkor Temple tour with guide - Hotel Drop | B87: 40 | C87: 94
A88: Siem Reap Hotel - Floating village with guide - Hotel Drop | B88: 30 | C88: 94
A89: Siem Reap Hotel - Siem Reap Airport Drop | C89: 68
A91: Siem Reap Hotel - Drive By Car - Phnom Penh Hotel Drop | C91: 162
A92: Phnom Penh Hotel - Royal Palace and Silver Pagoda with guide - National Museum and Tuol Sleng Museum - Choeung Ek - Market By Own - Hotel Drop | B92: 31 | C92: 100
A93: Phnom Penh Hotel - Phnom Penh Airport Drop | C93: 44
A94: --- | B94: 0

Sheet Sheet4
F1: HANOI | J1: HANOI | M1: HANOI
F2: 4 star | J2: 5 STAR | M2: 3 STAR
A3: HOTEL NAME (Room Category) | B3: PRICE | F3: The Q hotel Ha Noi ( Superior ) | G3: =E6 -> 71.041667 | J3: GRAND VISTA HANOI HOTEL (Premium Suite) | K3: =E33 -> 0 | M3: BRILLIANT HANOI HOTEL (Deluxe No window) | N3: =E21 -> 50.416667
A4: HANOI | B4: PRICE | D4: 0 | E4: 0 | F4: The Q hotel Ha Noi ( Deluxe ) | G4: =E7 -> 77.916667 | J4: GRAND VISTA HANOI HOTEL (Executive Suite) | K4: =E34 -> 84.791667 | M4: BRILLIANT HANOI HOTEL (Junior Window City View) | N4: =E22 -> 64.166667
A5: 4 star | D5: =(B5/24000) -> 0 | E5: =D5+D5*10% -> 0 | F5: Rex Hanoi Hotel (superior No window ) | G5: =E8 -> 68.75 | J5: Apricot Hotel ( SKETCH Room ) | K5: =E35 -> 132.91667 | M5: HANOI ANISE HOTEL & SPA (Superior TW/DBL) | N5: =E23 -> 32.083333
A6: The Q hotel Ha Noi ( Superior ) | B6: 1550000 | D6: =(B6/24000) -> 64.583333 | E6: =D6+D6*10% -> 71.041667 | F6: Rex Hanoi Hotel (Deluxe internal window) | G6: =E9 -> 77.916667 | J6: Apricot Hotel (CANVAS Room) | K6: =E36 -> 114.58333 | M6: HANOI ANISE HOTEL & SPA ( Deluxe City View TW/DBL) | N6: =E24 -> 36.666667
A7: The Q hotel Ha Noi ( Deluxe ) | B7: 1700000 | D7: =(B7/24000) -> 70.833333 | E7: =D7+D7*10% -> 77.916667 | F7: NESTA HOTEL - WEST LAKE (Deluxe City View ) | G7: =E10 -> 59.583333 | J7: PAN PACIFIC HANOI (Deluxe Room) | K7: =E37 -> 165 | M7: DIAMOND LEGEND HOTEL (Superior Room window inside) | N7: =E25 -> 29.791667
A8: Rex Hanoi Hotel (superior No window ) | B8: 1500000 | D8: =(B8/24000) -> 62.5 | E8: =D8+D8*10% -> 68.75 | F8: NESTA HOTEL - WEST LAKE (Deluxe Lake View) | G8: =E11 -> 64.166667 | J8: PAN PACIFIC HANOI (Premier Lake View Room) | K8: =E38 -> 192.5 | M8: DIAMOND LEGEND HOTEL (Deluxe Room Window or Balcony) | N8: =E26 -> 36.666667
A9: Rex Hanoi Hotel (Deluxe internal window) | B9: 1700000 | D9: =(B9/24000) -> 70.833333 | E9: =D9+D9*10% -> 77.916667 | F9: VICTORIA HOI AN BEACH RESORT & SPA ( Superior River View) | G9: =E12 -> 142.08333 | J9: LOTTE HOTEL ( Deluxe Room ) | K9: =E39 -> 159.5 | M9: Little Diamond Hotel Hanoi ( Superior Double no window) | N9: =E27 -> 25.208333
A10: NESTA HOTEL - WEST LAKE (Deluxe City View *) | B10: 1300000 | D10: =(B10/24000) -> 54.166667 | E10: =D10+D10*10% -> 59.583333 | F10: VICTORIA HOI AN BEACH RESORT & SPA ( Superior Garden View) | G10: =E13 -> 169.58333 | J10: LOTTE HOTEL ( Club Junior Suite) | K10: =E40 -> 231 | M10: Little Diamond Hotel Hanoi (Junior Double window inside) | N10: =E28 -> 29.791667
A11: NESTA HOTEL - WEST LAKE (Deluxe Lake View) | B11: 1400000 | D11: =(B11/24000) -> 58.333333 | E11: =D11+D11*10% -> 64.166667 | F11: Authentic Hanoi Boutique Hotel (Deluxe No window) | G11: =E14 -> 59.583333 | J11: Dolce by Wyndham Hanoi Golden Lake ( Golden Deluxe) | K11: =E41 -> 357.5 | M11: JaCosmo Hotel and Spa (Superior room) | N11: =E29 -> 41.25
A12: VICTORIA HOI AN BEACH RESORT & SPA ( Superior River View) | B12: 3100000 | D12: =(B12/24000) -> 129.16667 | E12: =D12+D12*10% -> 142.08333 | G12: =E15 -> 0 | J12: Dolce by Wyndham Hanoi Golden Lake (Golden Executive) | K12: =E42 -> 385 | M12: JaCosmo Hotel and Spa (Deluxe room) | N12: =E30 -> 45.833333
A13: VICTORIA HOI AN BEACH RESORT & SPA ( Superior Garden View) | B13: 3700000 | D13: =(B13/24000) -> 154.16667 | E13: =D13+D13*10% -> 169.58333 | F13: Authentic Hanoi Boutique Hotel (Deluxe with window external view) | G13: =E16 -> 73.333333 | J13: OAKWOOD RESIDENCE HANOI ( Studio Room) | K13: =E43 -> 93.729167
A14: Authentic Hanoi Boutique Hotel (Deluxe No window) | B14: 1300000 | D14: =(B14/24000) -> 54.166667 | E14: =D14+D14*10% -> 59.583333 | F14: The Hanoi Club Hotel & Residences (Superior (view phố) | G14: =E17 -> 91.666667 | J14: OAKWOOD RESIDENCE HANOI (Two Bed Room) | K14: =E44 -> 174.625 | M14: Cruise
D15: =(B15/24000) -> 0 | E15: =D15+D15*10% -> 0 | F15: The Hanoi Club Hotel & Residences ( Deluxe (view 1 phần hồ) | G15: =E18 -> 100.83333 | M15: ERA CRUISES ( Terrace Suite ) | N15: =E47 -> 367.58333
A16: Authentic Hanoi Boutique Hotel (Deluxe with window external view) | B16: 1600000 | D16: =(B16/24000) -> 66.666667 | E16: =D16+D16*10% -> 73.333333 | J16: Cruise | M16: ERA CRUISES (King Terrace Suite) | N16: =E48 -> 412.0875
A17: The Hanoi Club Hotel & Residences (Superior (view phố) | B17: 2000000 | D17: =(B17/24000) -> 83.333333 | E17: =D17+D17*10% -> 91.666667 | F17: Cruise | J17: ERA CRUISES ( Terrace Suite ) | K17: =E47 -> 367.58333 | M17: HẠ LONG BAY AQUAMARINE CRUISE (Junior Suite) | N17: =E49 -> 229.16667
A18: The Hanoi Club Hotel & Residences ( Deluxe (view 1 phần hồ) | B18: 2200000 | D18: =(B18/24000) -> 91.666667 | E18: =D18+D18*10% -> 100.83333 | F18: ERA CRUISES ( Terrace Suite ) | G18: =E47 -> 367.58333 | J18: ERA CRUISES (King Terrace Suite) | K18: =E48 -> 412.0875 | M18: HẠ LONG BAY AQUAMARINE CRUISE ( Senior Suite) | N18: =E50 -> 242.91667
D19: =(B19/24000) -> 0 | E19: =D19+D19*10% -> 0 | F19: ERA CRUISES (King Terrace Suite) | G19: =E48 -> 412.0875 | J19: HẠ LONG BAY AQUAMARINE CRUISE (Junior Suite) | K19: =E49 -> 229.16667 | M19: AMBASSADOR CRUISE (Executive Ambassador Balcony) | N19: =E51 -> 411.125
A20: 3 STAR | D20: =(B20/24000) -> 0 | E20: =D20+D20*10% -> 0 | F20: HẠ LONG BAY AQUAMARINE CRUISE (Junior Suite) | G20: =E49 -> 229.16667 | J20: HẠ LONG BAY AQUAMARINE CRUISE ( Senior Suite) | K20: =E50 -> 242.91667 | M20: AMBASSADOR CRUISE (Ambassador Balcony Suite) | N20: =E52 -> 443.4375
A21: BRILLIANT HANOI HOTEL (Deluxe No window) | B21: 1100000 | D21: =(B21/24000) -> 45.833333 | E21: =D21+D21*10% -> 50.416667 | F21: HẠ LONG BAY AQUAMARINE CRUISE ( Senior Suite) | G21: =E50 -> 242.91667 | J21: AMBASSADOR CRUISE (Executive Ambassador Balcony) | K21: =E51 -> 411.125 | M21: LA PANDORA CRUISE ( Suite Balcony) | N21: =E53 -> 24.75
A22: BRILLIANT HANOI HOTEL (Junior Window City View) | B22: 1400000 | D22: =(B22/24000) -> 58.333333 | E22: =D22+D22*10% -> 64.166667 | F22: AMBASSADOR CRUISE (Executive Ambassador Balcony) | G22: =E51 -> 411.125 | J22: AMBASSADOR CRUISE (Ambassador Balcony Suite) | K22: =E52 -> 443.4375 | M22: LA PANDORA CRUISE ( Family Suite Balcony) | N22: =E54 -> 26.583333
A23: HANOI ANISE HOTEL & SPA (Superior TW/DBL) | B23: 700000 | D23: =(B23/24000) -> 29.166667 | E23: =D23+D23*10% -> 32.083333 | F23: AMBASSADOR CRUISE (Ambassador Balcony Suite) | G23: =E52 -> 443.4375 | J23: LA PANDORA CRUISE ( Suite Balcony) | K23: =E53 -> 24.75 | M23: ALISA PREMIER CRUISE ( Junior suite) | N23: =E55 -> 289.575
A24: HANOI ANISE HOTEL & SPA ( Deluxe City View TW/DBL) | B24: 800000 | D24: =(B24/24000) -> 33.333333 | E24: =D24+D24*10% -> 36.666667 | F24: LA PANDORA CRUISE ( Suite Balcony) | G24: =E53 -> 24.75 | J24: LA PANDORA CRUISE ( Family Suite Balcony) | K24: =E54 -> 26.583333 | M24: ALISA PREMIER CRUISE (Senior Balcony Suite) | N24: =E56 -> 300.7125
A25: DIAMOND LEGEND HOTEL (Superior Room window inside) | B25: 650000 | D25: =(B25/24000) -> 27.083333 | E25: =D25+D25*10% -> 29.791667 | F25: LA PANDORA CRUISE ( Family Suite Balcony) | G25: =E54 -> 26.583333 | J25: ALISA PREMIER CRUISE ( Junior suite) | K25: =E55 -> 289.575 | M25: AQUAMARINE CRUISE (Junior Suite) | N25: =E57 -> 229.16667
A26: DIAMOND LEGEND HOTEL (Deluxe Room Window or Balcony) | B26: 800000 | D26: =(B26/24000) -> 33.333333 | E26: =D26+D26*10% -> 36.666667 | F26: ALISA PREMIER CRUISE ( Junior suite) | G26: =E55 -> 289.575 | J26: ALISA PREMIER CRUISE (Senior Balcony Suite) | K26: =E56 -> 300.7125 | M26: AQUAMARINE CRUISE (Senior Suite) | N26: =E58 -> 242.91667
A27: Little Diamond Hotel Hanoi ( Superior Double no window) | B27: 550000 | D27: =(B27/24000) -> 22.916667 | E27: =D27+D27*10% -> 25.208333 | F27: ALISA PREMIER CRUISE (Senior Balcony Suite) | G27: =E56 -> 300.7125 | J27: AQUAMARINE CRUISE (Junior Suite) | K27: =E57 -> 229.16667 | M27: SWAN CRUISES ( Deluxe Double/Twin) | N27: =E59 -> 245.20833
A28: Little Diamond Hotel Hanoi (Junior Double window inside) | B28: 650000 | D28: =(B28/24000) -> 27.083333 | E28: =D28+D28*10% -> 29.791667 | F28: AQUAMARINE CRUISE (Junior Suite) | G28: =E57 -> 229.16667 | J28: AQUAMARINE CRUISE (Senior Suite) | K28: =E58 -> 242.91667 | M28: SWAN CRUISES (Suite Cabins) | N28: =E60 -> 267.3
A29: JaCosmo Hotel and Spa (Superior room) | B29: 900000 | D29: =(B29/24000) -> 37.5 | E29: =D29+D29*10% -> 41.25 | F29: AQUAMARINE CRUISE (Senior Suite) | G29: =E58 -> 242.91667 | J29: SWAN CRUISES ( Deluxe Double/Twin) | K29: =E59 -> 245.20833 | M29: SENA CRUISE ( Balcony Deluxe ) | N29: =E61 -> 267.3
A30: JaCosmo Hotel and Spa (Deluxe room) | B30: 1000000 | D30: =(B30/24000) -> 41.666667 | E30: =D30+D30*10% -> 45.833333 | F30: SWAN CRUISES ( Deluxe Double/Twin) | G30: =E59 -> 245.20833 | J30: SWAN CRUISES (Suite Cabins) | K30: =E60 -> 267.3 | M30: RITA CRUISE (STANDARD CABIN) | N30: =E62 -> 256.66667
D31: =(B31/24000) -> 0 | E31: =D31+D31*10% -> 0 | F31: SWAN CRUISES (Suite Cabins) | G31: =E60 -> 267.3 | J31: SENA CRUISE ( Balcony Deluxe ) | K31: =E61 -> 267.3 | M31: RITA CRUISE (JUNIOR SUITE) | N31: =E63 -> 311.66667
A32: 5 STAR | B32: PRICE | D32: =(B32/24000) -> #VALUE! | E32: =D32+D32*10% -> #VALUE! | F32: SENA CRUISE ( Balcony Deluxe ) | G32: =E61 -> 267.3 | J32: RITA CRUISE (STANDARD CABIN) | K32: =E62 -> 256.66667 | M32: LE JOURNEY CRUISE | N32: =E64 -> 222.75
B33: 0 | D33: =(B33/24000) -> 0 | E33: =D33+D33*10% -> 0 | F33: RITA CRUISE (STANDARD CABIN) | G33: =E62 -> 256.66667 | J33: RITA CRUISE (JUNIOR SUITE) | K33: =E63 -> 311.66667 | M33: SENA CRUISE ( Balcony Executive ) | N33: =E65 -> 289.575
A34: GRAND VISTA HANOI HOTEL (DELUXE ROOM) | B34: 1850000 | D34: =(B34/24000) -> 77.083333 | E34: =D34+D34*10% -> 84.791667 | F34: RITA CRUISE (JUNIOR SUITE) | G34: =E63 -> 311.66667 | J34: LE JOURNEY CRUISE | K34: =E64 -> 222.75 | M34: HERA CLASSIC BOUTIQUE (Deluxe Cabin with Ocean View) | N34: =E66 -> 220
A35: Apricot Hotel ( SKETCH Room ) | B35: 2900000 | D35: =(B35/24000) -> 120.83333 | E35: =D35+D35*10% -> 132.91667 | F35: LE JOURNEY CRUISE | G35: =E64 -> 222.75 | J35: SENA CRUISE ( Balcony Executive ) | K35: =E65 -> 289.575 | M35: HERA CLASSIC BOUTIQUE (Executive Suite Cabin with private balcony) | N35: =E67 -> 247.5
A36: Apricot Hotel (CANVAS Room) | B36: 2500000 | D36: =(B36/24000) -> 104.16667 | E36: =D36+D36*10% -> 114.58333 | F36: SENA CRUISE ( Balcony Executive ) | G36: =E65 -> 289.575 | J36: HERA CLASSIC BOUTIQUE (Deluxe Cabin with Ocean View) | K36: =E66 -> 220 | M36: HERA GRAND LUXURY CRUISE (Junior Suite Cabin with Ocean View) | N36: =E68 -> 247.5
A37: PAN PACIFIC HANOI (Deluxe Room) | B37: 3600000 | D37: =(B37/24000) -> 150 | E37: =D37+D37*10% -> 165 | F37: HERA CLASSIC BOUTIQUE (Deluxe Cabin with Ocean View) | G37: =E66 -> 220 | J37: HERA CLASSIC BOUTIQUE (Executive Suite Cabin with private balcony) | K37: =E67 -> 247.5 | M37: HERA GRAND LUXURY CRUISE (Ocean Suite Cabin with private balcony) | N37: =E69 -> 293.33333
A38: PAN PACIFIC HANOI (Premier Lake View Room) | B38: 4200000 | D38: =(B38/24000) -> 175 | E38: =D38+D38*10% -> 192.5 | F38: HERA CLASSIC BOUTIQUE (Executive Suite Cabin with private balcony) | G38: =E67 -> 247.5 | J38: HERA GRAND LUXURY CRUISE (Junior Suite Cabin with Ocean View) | K38: =E68 -> 247.5 | M38: HERA BOUTIQUE (Deluxe Cabin with Ocean View) | N38: =E70 -> 201.66667
A39: LOTTE HOTEL ( Deluxe Room ) | B39: 3480000 | D39: =(B39/24000) -> 145 | E39: =D39+D39*10% -> 159.5 | F39: HERA GRAND LUXURY CRUISE (Junior Suite Cabin with Ocean View) | G39: =E68 -> 247.5 | J39: HERA GRAND LUXURY CRUISE (Ocean Suite Cabin with private balcony) | K39: =E69 -> 293.33333 | M39: HERA BOUTIQUE (Executive Suite Cabin with private balcony) | N39: =E71 -> 229.16667
A40: LOTTE HOTEL ( Club Junior Suite) | B40: 5040000 | D40: =(B40/24000) -> 210 | E40: =D40+D40*10% -> 231 | F40: HERA GRAND LUXURY CRUISE (Ocean Suite Cabin with private balcony) | G40: =E69 -> 293.33333 | J40: HERA BOUTIQUE (Deluxe Cabin with Ocean View) | K40: =E70 -> 201.66667 | M40: HERA GRAND LUXURY CRUISE (Junior Suite Cabin with Ocean View) | N40: =E72 -> 229.16667
A41: Dolce by Wyndham Hanoi Golden Lake ( Golden Deluxe) | B41: 7800000 | D41: =(B41/24000) -> 325 | E41: =D41+D41*10% -> 357.5 | F41: HERA BOUTIQUE (Deluxe Cabin with Ocean View) | G41: =E70 -> 201.66667 | J41: HERA BOUTIQUE (Executive Suite Cabin with private balcony) | K41: =E71 -> 229.16667 | M41: HERA GRAND LUXURY CRUISE (Ocean Suite Cabin with private balcony) | N41: =E73 -> 275
A42: Dolce by Wyndham Hanoi Golden Lake (Golden Executive) | B42: 8400000 | D42: =(B42/24000) -> 350 | E42: =D42+D42*10% -> 385 | F42: HERA BOUTIQUE (Executive Suite Cabin with private balcony) | G42: =E71 -> 229.16667 | J42: HERA GRAND LUXURY CRUISE (Junior Suite Cabin with Ocean View) | K42: =E72 -> 229.16667 | M42: VERDURE LOTUS CLASSIC (Deluxe Room) | N42: =E74 -> 220
A43: OAKWOOD RESIDENCE HANOI ( Studio Room) | B43: 2045000 | D43: =(B43/24000) -> 85.208333 | E43: =D43+D43*10% -> 93.729167 | F43: HERA GRAND LUXURY CRUISE (Junior Suite Cabin with Ocean View) | G43: =E72 -> 229.16667 | J43: HERA GRAND LUXURY CRUISE (Ocean Suite Cabin with private balcony) | K43: =E73 -> 275 | M43: VERDURE LOTUS CLASSIC (Executive Room) | N43: =E75 -> 238.33333
A44: OAKWOOD RESIDENCE HANOI (Two Bed Room) | B44: 3810000 | D44: =(B44/24000) -> 158.75 | E44: =D44+D44*10% -> 174.625 | F44: HERA GRAND LUXURY CRUISE (Ocean Suite Cabin with private balcony) | G44: =E73 -> 275 | J44: VERDURE LOTUS CLASSIC (Deluxe Room) | K44: =E74 -> 220 | M44: VERDURE LOTUS LUXURY (Deluxe Room) | N44: =E76 -> 238.33333
D45: =(B45/24000) -> 0 | E45: =D45+D45*10% -> 0 | F45: VERDURE LOTUS CLASSIC (Deluxe Room) | G45: =E74 -> 220 | J45: VERDURE LOTUS CLASSIC (Executive Room) | K45: =E75 -> 238.33333 | M45: VERDURE LOTUS LUXURY (Executive Room) | N45: =E77 -> 256.66667
A46: Cruise | D46: =(B46/24000) -> 0 | E46: =D46+D46*10% -> 0 | F46: VERDURE LOTUS CLASSIC (Executive Room) | G46: =E75 -> 238.33333 | J46: VERDURE LOTUS LUXURY (Deluxe Room) | K46: =E76 -> 238.33333 | M46: VERDURE LOTUS Premium CRUISE ( Deluxe Room ) | N46: =E78 -> 229.16667
A47: ERA CRUISES ( Terrace Suite ) | B47: 8020000 | D47: =(B47/24000) -> 334.16667 | E47: =D47+D47*10% -> 367.58333 | F47: VERDURE LOTUS LUXURY (Deluxe Room) | G47: =E76 -> 238.33333 | J47: VERDURE LOTUS LUXURY (Executive Room) | K47: =E77 -> 256.66667 | M47: VERDURE LOTUS Premium CRUISE (Executive Room) | N47: =E79 -> 247.5
A48: ERA CRUISES (King Terrace Suite) | B48: 8991000 | D48: =(B48/24000) -> 374.625 | E48: =D48+D48*10% -> 412.0875 | F48: VERDURE LOTUS LUXURY (Executive Room) | G48: =E77 -> 256.66667 | J48: VERDURE LOTUS Premium CRUISE ( Deluxe Room ) | K48: =E78 -> 229.16667 | M48: LA REGINA CLASSIC (Deluxe Ocean View ) | N48: =E80 -> 192.5
A49: HẠ LONG BAY AQUAMARINE CRUISE (Junior Suite) | B49: 5000000 | D49: =(B49/24000) -> 208.33333 | E49: =D49+D49*10% -> 229.16667 | F49: VERDURE LOTUS Premium CRUISE ( Deluxe Room ) | G49: =E78 -> 229.16667 | J49: VERDURE LOTUS Premium CRUISE (Executive Room) | K49: =E79 -> 247.5 | M49: LA REGINA CLASSIC (Premium Ocean View) | N49: =E81 -> 201.66667
A50: HẠ LONG BAY AQUAMARINE CRUISE ( Senior Suite) | B50: 5300000 | D50: =(B50/24000) -> 220.83333 | E50: =D50+D50*10% -> 242.91667 | F50: VERDURE LOTUS Premium CRUISE (Executive Room) | G50: =E79 -> 247.5 | J50: LA REGINA CLASSIC (Deluxe Ocean View ) | K50: =E80 -> 192.5 | M50: LA REGINA GRAND (Bai Tu Long Suite ) | N50: =E82 -> 302.5
A51: AMBASSADOR CRUISE (Executive Ambassador Balcony) | B51: 8970000 | D51: =(B51/24000) -> 373.75 | E51: =D51+D51*10% -> 411.125 | F51: LA REGINA CLASSIC (Deluxe Ocean View ) | G51: =E80 -> 192.5 | J51: LA REGINA CLASSIC (Premium Ocean View) | K51: =E81 -> 201.66667 | M51: LA REGINA GRAND (Ha Long Suite ) | N51: =E83 -> 325.41667
A52: AMBASSADOR CRUISE (Ambassador Balcony Suite) | B52: 9675000 | D52: =(B52/24000) -> 403.125 | E52: =D52+D52*10% -> 443.4375 | F52: LA REGINA CLASSIC (Premium Ocean View) | G52: =E81 -> 201.66667 | J52: LA REGINA GRAND (Bai Tu Long Suite ) | K52: =E82 -> 302.5 | M52: LA REGINA LEGEND CRUISE (Princess Suite Doulbe/ Twin) | N52: =E84 -> 293.33333
A53: LA PANDORA CRUISE ( Suite Balcony) | B53: 540000 | D53: =(B53/24000) -> 22.5 | E53: =D53+D53*10% -> 24.75 | F53: LA REGINA GRAND (Bai Tu Long Suite ) | G53: =E82 -> 302.5 | J53: LA REGINA GRAND (Ha Long Suite ) | K53: =E83 -> 325.41667 | M53: LA REGINA LEGEND CRUISE (Princess Premium Suite Doulbe/ Twin ) | N53: =E85 -> 316.25
A54: LA PANDORA CRUISE ( Family Suite Balcony) | B54: 580000 | D54: =(B54/24000) -> 24.166667 | E54: =D54+D54*10% -> 26.583333 | F54: LA REGINA GRAND (Ha Long Suite ) | G54: =E83 -> 325.41667 | J54: LA REGINA LEGEND CRUISE (Princess Suite Doulbe/ Twin) | K54: =E84 -> 293.33333 | M54: LA REGINA ROYAL (Noble Suite Double/ Twin) | N54: =E86 -> 247.5
A55: ALISA PREMIER CRUISE ( Junior suite) | B55: 6318000 | D55: =(B55/24000) -> 263.25 | E55: =D55+D55*10% -> 289.575 | F55: LA REGINA LEGEND CRUISE (Princess Suite Doulbe/ Twin) | G55: =E84 -> 293.33333 | J55: LA REGINA LEGEND CRUISE (Princess Premium Suite Doulbe/ Twin ) | K55: =E85 -> 316.25 | M55: LA REGINA ROYAL (Imperial Suite Double/ Twin) | N55: =E87 -> 261.25
A56: ALISA PREMIER CRUISE (Senior Balcony Suite) | B56: 6561000 | D56: =(B56/24000) -> 273.375 | E56: =D56+D56*10% -> 300.7125 | F56: LA REGINA LEGEND CRUISE (Princess Premium Suite Doulbe/ Twin ) | G56: =E85 -> 316.25 | J56: LA REGINA ROYAL (Noble Suite Double/ Twin) | K56: =E86 -> 247.5 | M56: DELASEA HALONG ( Deluxe City View ) | N56: =E88 -> 55
A57: AQUAMARINE CRUISE (Junior Suite) | B57: 5000000 | D57: =(B57/24000) -> 208.33333 | E57: =D57+D57*10% -> 229.16667 | F57: LA REGINA ROYAL (Noble Suite Double/ Twin) | G57: =E86 -> 247.5 | J57: LA REGINA ROYAL (Imperial Suite Double/ Twin) | K57: =E87 -> 261.25 | M57: DELASEA HALONG ( Deluxe Ocean View ) | N57: =E89 -> 66.458333
A58: AQUAMARINE CRUISE (Senior Suite) | B58: 5300000 | D58: =(B58/24000) -> 220.83333 | E58: =D58+D58*10% -> 242.91667 | F58: LA REGINA ROYAL (Imperial Suite Double/ Twin) | G58: =E87 -> 261.25 | J58: DELASEA HALONG ( Deluxe City View ) | K58: =E88 -> 55 | M58: Le Theatre Cruises ( Junior Suite) | N58: =E90 -> 297.91667
... A93: Oriental Sails! ( Deluxe Balcony) | B93: 0 | D93: =(B93/24000) -> 0 | E93: =D93+D93*10% -> 0 | F93: Amanda cruise (Deluxe Cabin with Ocean View) | G93: =E122 -> 210.83333 | J93: Amanda cruise ( Junior Suite Cabin with Ocean View) | K93: =E123 -> 229.16667 | M93: OMKARA DIAMOND DAY CRUISE ( Deluxe Cabin with Veg & Non Veg Combo Meals ) | N93: =E125 -> 389.8125
A94: SCARLET PEARL ( Silver Pearl) | B94: 7450000 | D94: =(B94/24000) -> 310.41667 | E94: =D94+D94*10% -> 341.45833 | F94: Amanda cruise ( Junior Suite Cabin with Ocean View) | G94: =E123 -> 229.16667 | J94: OMKARA DIAMOND DAY CRUISE ( Deluxe Cabin with Veg Meals ) | K94: =E124 -> 367.5375
A95: SCARLET PEARL ( Golden Pearl) | B95: 10080000 | D95: =(B95/24000) -> 420 | E95: =D95+D95*10% -> 462 | F95: OMKARA DIAMOND DAY CRUISE ( Deluxe Cabin with Veg Meals ) | G95: =E124 -> 367.5375 | J95: OMKARA DIAMOND DAY CRUISE ( Deluxe Cabin with Veg & Non Veg Combo Meals ) | K95: =E125 -> 389.8125 | M95: DANANG
A96: PELICAN GLORY GROUP ( Deluxe Room) | B96: 5151600 | D96: =(B96/24000) -> 214.65 | E96: =D96+D96*10% -> 236.115 | F96: OMKARA DIAMOND DAY CRUISE ( Deluxe Cabin with Veg & Non Veg Combo Meals ) | G96: =E125 -> 389.8125 | M96: 3 STAR
A97: PELICAN GLORY GROUP (Royal Suite) | B97: 7606000 | D97: =(B97/24000) -> 316.91667 | E97: =D97+D97*10% -> 348.60833 | J97: DANANG | M97: The Leaf Boutique Hotel ( Deluxe City View (4) ) | N97: =E154 -> 43.541667
A98: PARADISE GRAND CRUISE (Grand Balcony) | B98: 7700000 | D98: =(B98/24000) -> 320.83333 | E98: =D98+D98*10% -> 352.91667 | F98: DANANG | J98: 5 STAR | M98: The Leaf Boutique Hotel ( Superior Triple No View) | N98: =E155 -> 50.416667
A99: PARADISE GRAND CRUISE (Executive Grand Balcony) | B99: 8250000 | D99: =(B99/24000) -> 343.75 | E99: =D99+D99*10% -> 378.125 | F99: 4 STAR | J99: Daisy Boutique Hotel & Apartment ( Deluxe Double Room with Balcony and Garden View) | K99: =E141 -> 32.083333 | M99: GOLDEN LOTUS GRAND HOTEL ( DELUXE DBL ROOM ) | N99: =E156 -> 52.708333
A100: Novotel Ha Long ( Standard Room) | B100: 1850000 | D100: =(B100/24000) -> 77.083333 | E100: =D100+D100*10% -> 84.791667 | F100: STELLA MARIS BEACH DANANG ( SUPERIOR) | G100: =E129 -> 52.708333 | J100: Daisy Boutique Hotel & Apartment (Studio Double Room with Garden View) | K100: =E142 -> 36.666667 | M100: GOLDEN LOTUS GRAND HOTEL ( PREMIUM TRIPLE ROOM ) | N100: =E157 -> 75.625
A101: Novotel Ha Long ( Superior Room) | B101: 2200000 | D101: =(B101/24000) -> 91.666667 | E101: =D101+D101*10% -> 100.83333 | F101: STELLA MARIS BEACH DANANG ( DELUXE PARTIAL SEAVIEW) | G101: =E130 -> 61.875 | J101: FOUR POINTS BY SHERATON DANANG (Superior King Ocean View) | K101: =E143 -> 203.95833 | M101: Royal Family Hotel Da Nang ( Superior Double/Twin/2pax) | N101: =E158 -> 64.166667
A102: ATHENA LUXURY CRUISE ( EXECUTIVE Suite ) | B102: 6240000 | D102: =(B102/24000) -> 260 | E102: =D102+D102*10% -> 286 | F102: GOLDEN LOTUS LUXURY HOTEL ( Lotus Deluxe ) | G102: =E131 -> 0.0605 | J102: FOUR POINTS BY SHERATON DANANG ( Deluxe King Ocean View ) | K102: =E144 -> 226.875 | M102: Royal Family Hotel Da Nang ( Deluxe Double/Twin/2pax | N102: =E159 -> 82.5
A103: ATHENA LUXURY CRUISE ( (ELEGANT Suite) | B103: 6720000 | D103: =(B103/24000) -> 280 | E103: =D103+D103*10% -> 308 | F103: GOLDEN LOTUS LUXURY HOTEL ( Junior Suite ) | G103: =E132 -> 0.13452083 | J103: Eden Ocean View Đà Nẵng ( Classic Double ) | K103: =E145 -> 34.375
A104: ATHENA ROYAL CRUISE (EXECUTIVE ROYAL Suite) | B104: 6480000 | D104: =(B104/24000) -> 270 | E104: =D104+D104*10% -> 297 | F104: THE CODE HOTEL & SPA DA NANG ( Superior) | G104: =E133 -> 30.708333 | J104: Eden Ocean View Đà Nẵng ( Premium Sea View ) | K104: =E146 -> 38.958333 | M104: Ho Chi Minh
A105: ATHENA ROYAL CRUISE (ELEGANT ROYAL Suite) | B105: 6960000 | D105: =(B105/24000) -> 290 | E105: =D105+D105*10% -> 319 | F105: THE CODE HOTEL & SPA DA NANG ( Deluxe City view) | G105: =E134 -> 33 | J105: TIA Wellness Resort (One Bedroom Pool Villa) | K105: =E147 -> 592.16667 | M105: 3 STAR
A106: SIGNATURE HALONG CRUISE (JUNIOR SUITE) | B106: 5760000 | D106: =(B106/24000) -> 240 | E106: =D106+D106*10% -> 264 | F106: DRACO HOTEL & SUITES DANANG (Superior Room) | G106: =E135 -> 38.958333 | J106: TIA Wellness Resort (Two Bedroom Pool Villa) | K106: =E148 -> 844.06667
A107: SIGNATURE HALONG CRUISE (SENIOR SUITE) | B107: 6240000 | D107: =(B107/24000) -> 260 | E107: =D107+D107*10% -> 286 | F107: DRACO HOTEL & SUITES DANANG (Deluxe City View) | G107: =E136 -> 43.541667 | J107: Altara Suites ( BLISS, PEACE SUITE (01 bedroom) | K107: =E149 -> 75.625 | M107: Avanti Boutique Hotel ( Superior no window ) | N107: =E191 -> 36.666667
A108: SIGNATURE ROYAL CRUISE (JUNIOR SUITE) | B108: 5760000 | D108: =(B108/24000) -> 240 | E108: =D108+D108*10% -> 264 | F108: Cicilia Danang Hotels & Spa ( Deluxe City View ) | G108: =E137 -> 32.083333 | J108: Altara Suites ( HARMONY SUITE (02 bedrooms) | K108: =E150 -> 93.958333 | M108: Avanti Boutique Hotel ( Deluxe have window ) | N108: =E192 -> 48.125
A109: SIGNATURE ROYAL CRUISE (SENIOR SUITE ) | B109: 6240000 | D109: =(B109/24000) -> 260 | E109: =D109+D109*10% -> 286 | F109: Cicilia Danang Hotels & Spa (Junior Suite Ocean View ) | G109: =E138 -> 58.666667 | M109: Queen Ann Hotel Sai Gon ( Deluxe With Window ) | N109: =E193 -> 45.833333
A110: DORA LUXURY CRUISE (Junior Suite) | B110: 6600000 | D110: =(B110/24000) -> 275 | E110: =D110+D110*10% -> 302.5 | J110: Ho chi minh | M110: Queen Ann Hotel Sai Gon ( Premier With Window ) | N110: =E194 -> 50.416667
A111: DORA LUXURY CRUISE (Senior Suite) | B111: 7000000 | D111: =(B111/24000) -> 291.66667 | E111: =D111+D111*10% -> 320.83333 | F111: Ho Chi Minh | J111: 5 STAR | M111: Aluna Ben Thanh Hotel ( Schroeder (Window) ) | N111: =E195 -> 114.58333
A112: Bai Tho Junks! ( Deluxe Ocean View) | B112: 5700000 | D112: =(B112/24000) -> 237.5 | E112: =D112+D112*10% -> 261.25 | F112: 4 STAR | J112: REX SAIGON HO CHI MINH ( Rex Suite) | K112: =E177 -> 137.5 | M112: Aluna Ben Thanh Hotel ( Premier(Window) | N112: =E196 -> 105.41667
A113: Bai Tho Junks! ( Suite Ocean View Balcony) | B113: 6840000 | D113: =(B113/24000) -> 285 | E113: =D113+D113*10% -> 313.5 | F113: Paragon Saigon Hotel ( Deluxe Window (Queen-bed, Twin-bed) | G113: =E163 -> 90.75 | J113: REX SAIGON HO CHI MINH (Executive Premium) | K113: =E178 -> 148.95833 | M113: Dai Nam Boutique Hotel ( DELUXE ) SGL/DBL | N113: =E197 -> 55
A114: GOLDEN CRUISE (LUXURY) | B114: 5600000 | D114: =(B114/24000) -> 233.33333 | E114: =D114+D114*10% -> 256.66667 | F114: Paragon Saigon Hotel ( Premier window Sakura) | G114: =E164 -> 110.91667 | J114: Eastin Grand Hotel Saigon ( Superior Deluxe Single/Double) | K114: =E179 -> 78.145833 | M114: Dai Nam Boutique Hotel (EXECUTIVE ) SGL/DBL | N114: =E198 -> 64.166667
A115: GOLDEN CRUISE (SUITE) | B115: 10000000 | D115: =(B115/24000) -> 416.66667 | E115: =D115+D115*10% -> 458.33333 | F115: First Hotel ( Deluxe (30 m2) | G115: =E165 -> 41.25 | J115: Eastin Grand Hotel Saigon ( Deluxe Single/Double ) | K115: =E180 -> 88.229167
A116: A la carte halong bay hotel (Premier City View) | B116: 1700000 | D116: =(B116/24000) -> 70.833333 | E116: =D116+D116*10% -> 77.916667 | F116: First Hotel (Superior 20 m2)) | G116: =E166 -> 38.958333 | J116: Roseland Sweet Hotel & Spa! DELUXE NO WINDOW (Double) | K116: =E181 -> 68.75 | M116: Phu Quoc
A117: A la carte halong bay hotel (Executive Bay View ) | B117: 2100000 | D117: =(B117/24000) -> 87.5 | E117: =D117+D117*10% -> 96.25 | F117: Royal Hotel Saigon ( DELUXE ) | G117: =E167 -> 75.625 | J117: Roseland Sweet Hotel & Spa ( PREMIUM DELUXE ) | K117: =E182 -> 73.333333 | M117: 3 STAR
A118: Hotel Sol Hạ Long ( Premier Suite ) | B118: 2100000 | D118: =(B118/24000) -> 87.5 | E118: =D118+D118*10% -> 96.25 | F118: Royal Hotel Saigon (SUPER DELUXE ) | G118: =E168 -> 84.791667 | J118: Oakwood Residence Saigon! ( Studio Apartment (45 sqm) | K118: =E183 -> 111.375 | M118: Gaia Hotel Phu Quoc ( Standard ocean view Double/Twin) | N118: =E228 -> 27.5
A119: Hotel Sol Hạ Long ( Junior Suite ) | B119: 1950000 | D119: =(B119/24000) -> 81.25 | E119: =D119+D119*10% -> 89.375 | F119: 0 | G119: =E169 -> 0 | J119: Oakwood Residence Saigon! ( 01 Bed-room Apartment (51sqm) | K119: =E184 -> 121.91667 | M119: Gaia Hotel Phu Quoc ( Deluxe ocean view Double có Ban Công | N119: =E229 -> 34.375
A120: NOSTALGIA CRUISE (Princess Suite) | B120: 9234000 | D120: =(B120/24000) -> 384.75 | E120: =D120+D120*10% -> 423.225 | F120: Saigon Domaine Luxury Residences ( 1-Bedroom Suite ) | G120: =E170 -> 118.02083 | J120: Equatorial Ho Chi Minh City ( Deluxe ) | K120: =E185 -> 103.58333
A121: NOSTALGIA CRUISE (King Suite) | B121: 13608000 | D121: =(B121/24000) -> 567 | E121: =D121+D121*10% -> 623.7 | F121: Somerset CHANCELLOR COURT HO CHI MINH CITY (Executive Room) | G121: =E171 -> 106.53958 | J121: Equatorial Ho Chi Minh City ( Premier ) | K121: =E186 -> 126.5 | M121: Hoi AN
A122: Amanda cruise (Deluxe Cabin with Ocean View) | B122: 4600000 | D122: =(B122/24000) -> 191.66667 | E122: =D122+D122*10% -> 210.83333 | F122: Somerset CHANCELLOR COURT HO CHI MINH CITY ( Premier Room ) | G122: =E172 -> 111.73708 | M122: 3 STAR
A123: Amanda cruise ( Junior Suite Cabin with Ocean View) | B123: 5000000 | D123: =(B123/24000) -> 208.33333 | E123: =D123+D123*10% -> 229.16667 | F123: Ramada Encore By Wyndham Sai Gon Junior Deluxe | G123: =E173 -> 68.75 | J123: Phu Quoc | M123: Eco Lux Riverside Hotel & Spa Hoi An ( Superior room with balcony/window (D/T) | N123: =E233 -> 32.083333
A124: OMKARA DIAMOND DAY CRUISE ( Deluxe Cabin with Veg Meals ) | B124: 8019000 | D124: =(B124/24000) -> 334.125 | E124: =D124+D124*10% -> 367.5375 | F124: Ramada Encore By Wyndham Sai Gon Premium Deluxe | G124: =E174 -> 73.333333 | J124: 5 STAR | M124: Eco Lux Riverside Hotel & Spa Hoi An (Royal Honeymoon Suite with balcony (D) | N124: =E234 -> 59.583333
A125: OMKARA DIAMOND DAY CRUISE ( Deluxe Cabin with Veg & Non Veg Combo Meals ) | B125: 8505000 | D125: =(B125/24000) -> 354.375 | E125: =D125+D125*10% -> 389.8125 | J125: Best Western Premier Sonasea Phu Quoc ( Deluxe King or Twin with Balcony) | K125: =E213 -> 82.5 | M125: KIMAN HOTEL ( Deluxe Garden View) | N125: =E235 -> 33
D126: =(B126/24000) -> 0 | E126: =D126+D126*10% -> 0 | F126: Phu Quoc | J126: Best Western Premier Sonasea Phu Quoc ( Premier Deluxe King or Twin with Seaview) | K126: =E214 -> 91.666667 | M126: KIMAN HOTEL ( Deluxe City View) | N126: =E236 -> 35.75
A127: DANANG | D127: =(B127/24000) -> 0 | E127: =D127+D127*10% -> 0 | F127: 4 star | J127: Meliã Vinpearl Phu Quoc ( 1-Bedroom villa lake view with private pool) | K127: =E215 -> 334.58333
A128: 4 STAR | D128: =(B128/24000) -> 0 | E128: =D128+D128*10% -> 0 | F128: Sea Sense Resort ( Deluxe Garden View ) | G128: =E202 -> 74.25 | J128: Meliã Vinpearl Phu Quoc (2-Bedroom villa lake view with private pool) | K128: =E216 -> 559.16667 | M128: SAPA
A129: STELLA MARIS BEACH DANANG ( SUPERIOR) | B129: 1150000 | D129: =(B129/24000) -> 47.916667 | E129: =D129+D129*10% -> 52.708333 | F129: Sea Sense Resort ( Sea View Villa ) | G129: =E203 -> 99 | J129: Sheraton Phu Quoc Long Beach Resort! ( Standard with Ocean View) | K129: =E217 -> 126.72917 | M129: 3 STAR
A130: STELLA MARIS BEACH DANANG ( DELUXE PARTIAL SEAVIEW) | B130: 1350000 | D130: =(B130/24000) -> 56.25 | E130: =D130+D130*10% -> 61.875 | F130: Cassia Cottage Resort & Spa (GARDEN COTTAGE) | G130: =E204 -> 185.80833 | J130: Sheraton Phu Quoc Long Beach Resort! ( Premium with Ocean View) | K130: =E218 -> 159.04167 | M130: Sapa Horizon Hotel ( Superior room with balcony (Street, City view) | N130: =E297 -> 66.458333
A131: GOLDEN LOTUS LUXURY HOTEL ( Lotus Deluxe ) | B131: 1320 | D131: =(B131/24000) -> 0.055 | E131: =D131+D131*10% -> 0.0605 | F131: Cassia Cottage Resort & Spa ( MODERN DELUXE) | G131: =E205 -> 210.97083 | J131: Ocean Bay Resort & Spa Phu Quoc ( Jungle Bungalow) | K131: =E219 -> 93.5 | M131: Sapa Horizon Hotel (Deluxe room with balcony ) | N131: =E298 -> 75.625
A132: GOLDEN LOTUS LUXURY HOTEL ( Junior Suite ) | B132: 2935 | D132: =(B132/24000) -> 0.12229167 | E132: =D132+D132*10% -> 0.13452083 | F132: Famiana Resort & Spa Phu Quoc ( Deluxe Garden view) | G132: =E206 -> 106.79167 | J132: Ocean Bay Resort & Spa Phu Quoc ( Ocean Breeze Bungalow) | K132: =E220 -> 116.875
A133: THE CODE HOTEL & SPA DA NANG ( Superior) | B133: 670000 | D133: =(B133/24000) -> 27.916667 | E133: =D133+D133*10% -> 30.708333 | F133: Famiana Resort & Spa Phu Quoc (Premium Deluxe Garden View) | G133: =E207 -> 117.33333 | J133: Muong Thanh Luxury Phu Quoc Hotel ( Deluxe King/Twin) | K133: =E221 -> 73.333333
A134: THE CODE HOTEL & SPA DA NANG ( Deluxe City view) | B134: 720000 | D134: =(B134/24000) -> 30 | E134: =D134+D134*10% -> 33 | F134: Green Bay Phu Quoc Resort & Spa(Garden Villa 1-Bedroom) | G134: =E208 -> 147.58333 | J134: Muong Thanh Luxury Phu Quoc Hotel (Deluxe Triple) | K134: =E222 -> 96.25
...

Sheet Sheet1
D1: 5 * HOTEL | F1: International | I1: HANOI
D2: Hanoi Grand Plaza Hotel
D3: Grand Vista Hotel Hanoi | F3: Hanoi Airport ARRIVAL - T2 - PILLAR 10 1F Car pickup point. | I3: Hanoi Airport – 4 Hour Hanoi City Tour with guide - hotel - Dinner At Indian Restaurant - Hanoi Hotel drop (D)
D4: apricot hotel hanoi | F4: Halong Bay Cruise Terminal Dock | I4: Hnaoi Hotel - 100km 2 hours - Ninh Binh Tour - Tam Coc - Dinner At Indian Restaurant - Hotel Drop (B,D)
D5: Paradise Grand Cruise | F5: Danang Airport EXIT GATE PARKING Car pickup point. | I5: Hanoi Hotel - 200 Km 4 hours drive - Halong bay- 11:30 AM need to reach at Halong bay for cruise depart (B,Local L, Local D)
D6: TMS Hotel Da Nang Beach | F6: Ho Chi Minh Airport ARRIVAL - T2 - PILLAR 10 GF | I6: Halong Bay - Hanoi 4 hour 200 km - Dinner At Indian Restaurant - Hanoi Hotel drop, (B,Local Br,D)
D7: Four Points by Sheraton Danang | F7: Phu Quoc Airport EXIT GATE PARKING pickup point. | I7: Hanoi Hotel - HCM Complex - Tran Quoc Pagoda - Old Town 15 Min Tour - Cho Dong Xuan Market - Old Town For Shopping - Dinner At Indian Restaurant - Hanoi hotel drop (B,D)
F8: Siem Reap Airport Arrival Hall | I8: Hanoi Hotel - 300KM 6 hour Sapa - Moana Sculpture - Cat Cat Village tour - Dinner At Indian Restaurant - Sapa Hotel Drop (B,D)
D9: Equatorial Ho Chi Minh City | I9: Sapa Hotel - Fansipan Mountain with guide - 300km 6 hour drive - Dinner At Indian Restaurant - Hanoi Hotel drop (B,D)
D10: Sol by Meliá Phu Quoc | F10: Domestic | I10: Hanoi Hotel - Hanoi Airport Drop, Flight to --- (B) Vietjet Air VJ --- --- Departure
D12: 4 * Hotels | F12: Hanoi Airport T1 - ARRIVAL - E2 Car pickup point. | I12: DANANG
D13: Rex Hanoi Hotel | F13: Halong Bay Cruise Terminal Dock | I13: Danang Airport - Dinner At Indian Restaurant - Danang Hotel Drop (D)
A14: Arrival Date : January, 2024 | D14: Nesta West Lake Hotel Hanoi | F14: Danang Airport T1 ARRIVAL PILLAR 4,5 Car pickup point. | I14: Danang hotel - Ba Na Hills with guide - Dinner At Indian Restaurant - Danang hotel (B,D)
A15: Arrival Date : February, 2024 | D15: Le Journey Luxury Cruise | F15: Ho Chi Minh Airport T1 - ARRIVAL - A1 | I15: Danang hotel - Marble Mountain - Hoi An Ancient Town - Japanese Covered Bridge - Dinner At Indian Restaurant - Hotel Drop (B,D)
A16: Arrival Date : March, 2024 | D16: Hera Cruise | F16: Phu Quoc Airport EXIT GATE PARKING pickup point. | I16: Danang hotel - Coconut Village with guide - Basket Boat Ride - Hoi An Ancient Town Tour - Lantern Release On The River - Dinner At Indian Restaurant - Danang hotel Drop, 8:30 PM (B,D)
A17: Arrival Date : April, 2024 | D17: Stella Maris Beach Danang Hotel | F17: Siem Reap Airport Arrival Hall | I17: Danang Hotel - Danang Airport Drop, Flight to ---- (B) Vietjet Air VJ --- --- Departure
A18: Arrival Date : May, 2024 | D18: Golden Lotus Luxury Hotel Da Nang
A19: Arrival Date : June, 2024 | D19: Bay Hotel Ho Chi Minh | I19: HO CHI MINH
A20: Arrival Date : July, 2024 | D20: ramada encore ho chi minh | I20: Ho Chi Minh Airport - Dinner At Indian Restaurant - Ho Chi Minh Hotel Drop (D)
A21: Arrival Date : August, 2024 | D21: vinpearl resort and spa | I21: Ho Chi Minh Hotel - HCM city tour - Lunch Transfer - Notre Dame Cathedral, General Post Office, The city hall, Opera House - Reunification Hall - War Remnants Museum - Hop on Hop off city tour - Dinner At Indian Restaurant - Hotel Drop (B,D)
A22: Arrival Date : September, 2024 | I22: Ho Chi Minh Hotel - Mekong Delta (My Tho) with guide - Dinner At Indian Restaurant - HCM hotel drop (B,D)
A23: Arrival Date : October, 2024 | D23: 3 * Hotels | I23: HCM Hotel - Cu Chi Tunnel Tour with guide - Dinner At Indian Restaurant - hotel drop (B,D)
A24: Arrival Date : November, 2024 | D24: Diamond Legend Hotel | I24: HCM Hotel - HCM Airport Drop, Flight to ---- (B) Vietjet Air VJ --- --- Departure
A25: Arrival Date : December, 2024 | D25: Le Journey Classic Cruise
D26: Golden Lotus Grand Hotel | I26: PHU QUOC
A27: Departure Date : January, 2024 | D27: Ben Thanh Boutique Hotel | I27: Phu Quoc Airport - Dinner At Indian Restaurant - Phu Quoc Hotel Drop (D)
A28: Departure Date : February, 2024 | D28: Resort Arcadia Phú Quốc | I28: Phu Quoc Hotel - Vin Pearl Safari & Vin Wonders - 6 Theme park - Dinner At Indian Restaurant - Hotel Drop (B,D)
A29: Departure Date : March, 2024 | I29: Phu Quoc Hotel - Full Day - 3 Island tour in south by speedboat - Dinner At Indian Restaurant - Late Noon return hotel drop (B,D)
A30: Departure Date : April, 2024 | E30: Transport : 4 Seater Private Car | I30: Phu Quoc Hotel - Phu Quoc Airport Drop, Flight to --- (B) Vietjet Air VJ --- --- Departure
A31: Departure Date : May, 2024 | E31: Transport : 7 Seater Private Car
A32: Departure Date : June, 2024 | E32: Transport : 16 Seater Private Car | I32: SIEM REAP
A33: Departure Date : July, 2024 | E33: Transport : 29 Seater Private Car | I33: Siem Reap Airport - Hotel - Apsara Dance Show Dinner At Restaurant - Siem Reap Hotel Drop (D)
A34: Departure Date : August, 2024 | E34: Transport : 45 Seater Private Car | I34: Siem Reap Hotel - Angkor Temple tour with guide - Dinner At Indian Restaurant - Hotel Drop (B,D)
A35: Departure Date : September, 2024 | I35: Siem Reap Hotel - Floating village with guide - Dinner At Indian Restaurant - Hotel Drop (B,D)
A36: Departure Date : October, 2024 | I36: Siem Reap Hotel - Siem Reap Airport Drop (B)
A37: Departure Date : November, 2024
A38: Departure Date : December, 2024 | I38: PHNOM PENH
I39: Siem Reap Hotel - Drive By Car - Dinner At Indian Restaurant - Phnom Penh Hotel Drop (B,D)
I40: Phnom Penh Hotel - Royal Palace and Silver Pagoda with guide - National Museum and Tuol Sleng Museum - Choeung Ek - Market By Own - Dinner At Indian Restaurant - Hotel Drop (B,D)
I41: Phnom Penh Hotel - Phnom Penh Airport Drop (B)

Sheet Sheet3
A1: Hanoi Airport - Hanoi Hotel drop | B1: ● ARRIVAL HANOI, VIETNAM ♦ Arrive In Noi Bai International Airport. ♦ Our Private Car Will Pick You Up From The Airport And Head Towards The Hotel. ♦ Early Check-in is not included . Take Necessary Rest After Flight. ♦ Overnight stay in Hanoi.
A2: Hanoi Airport - Hanoi - 4 Hour Hanoi City Tour - Hanoi Hotel drop | B2: ● ARRIVAL HANOI - HANOI CITY TOUR, VIETNAM ♦ Arrive In Noi Bai International Airport. ♦ Our Private Car Will Pick You Up From The Airport And Head Towards The Hotel. ♦ Early Check-in is not included. Take Necessary Rest After Flight ♦ Check Out The Old Street Quarter For Hanoi City Tour – Visit The Temple of Literature, Vietnam’s first university, Hoan Kiem Lake & Ly Thai Statue, HCM Complex: Ho Chi Minh Mausoleum, One pillar Pagoda, Ba Dinh Square. ♦ 4 Hours tour then Check in Hotel. ♦ Overnight stay in Hanoi.
A3: Hanoi Airport - Hanoi - 4 Hour Hanoi City Tour - 50 Min Cyclo Tour - Hanoi Hotel Drop | B3: ● ARRIVAL HANOI - HANOI CITY TOUR - 50 MIN CYCLO TOUR, VIETNAM ♦ Arrive In Noi Bai International Airport. ♦ Our Private Car Will Pick You Up From The Airport And Head Towards The Hotel. ♦ Early Check-in is not included. Take Necessary Rest After Flight ♦ Check Out The Old Street Quarter For 4 hour Hanoi City Tour , 50 Min Cyclo Tour. ♦ After tour Check in Hotel. ♦ Overnight stay in Hanoi.
A4: Hanoi Airport - Hanoi - 4 Hour Hanoi City Tour - 50 Min Cyclo Tour - Water Puppet Show - Hanoi Hotel Drop | B4: ● ARRIVAL HANOI - HANOI CITY TOUR - 50 MIN CYCLO TOUR - WATER PUPPET SHOW, VIETNAM ♦ Arrive In Noi Bai International Airport. ♦ Our Private Car Will Pick You Up From The Airport And Head Towards The Hotel. ♦ Early Check-in is not included. Take Necessary Rest After Flight Check Out The Old Street Quarter For 4 hours Hanoi City Tour, 50 Min Cyclo Tour, Water Puppet Show. ♦ After tour Check in Hotel. ♦ Overnight stay in Hanoi.
A5: Hanoi Airport - Hanoi - 4 Hour Hanoi City Tour - Water Puppet Show - Hanoi Hotel Drop | B5: ● ARRIVAL HANOI - HANOI CITY TOUR - WATER PUPPET SHOW, VIETNAM ♦ Arrive In Noi Bai International Airport. ♦ Our Private Car Will Pick You Up From The Airport And Head Towards The Hotel. ♦ Check Into The Hotel, Take Necessary Rest After Flight Check Out The Old Street Quarter For 4 hour Hanoi City Tour, Water Puppet Show. ♦ After tour Check in Hotel. ♦ Overnight stay in Hanoi.
A6: Hanoi Hotel - Full Day Hanoi City Tour - Hotel Drop | B6: ● FULL DAY - HANOI CITY TOUR ♦ After breakfast, at 08:30 in the morning, our tour guide will pick you up and start with you on your journey to Full Day Hanoi City Tour driving per way for transfer. ♦ Visit Hanoi City Tour – Visit The Temple of Literature, Vietnam’s first university, Hoan Kiem Lake & Ly Thai Statue, HCM Complex: Ho Chi Minh Mausoleum, One pillar Pagoda, Ba Dinh Square. ♦ Evening come back to hotel, Overnight Stay in Hanoi.
A7: Hanoi Hotel - 4 Hours Hanoi City Tour - Hotel Drop | B7: ● HALF DAY - HANOI CITY TOUR ♦ After breakfast, at 08:30 in the morning, our tour guide will pick you up and start with you on your journey to Half day Hanoi City Tour driving per way for transfer. ♦ Visit Hanoi City Tour. ♦ Evening come back to hotel, Free Time For Shopping. Overnight Stay in Hanoi.
A8: Hanoi Airport - 100 KM 2 hours - Ninh Binh Tour - Tam Coc - Hotel Drop | B8: ● FULL DAY – NINH BINH TOUR ♦ (100 KM 2 hours Drive) ♦ Arrive In Noi Bai International Airport. ♦ Our Private Car Will Pick You Up From The Airport And Head Towards The Depart For Ninh Binh Province ♦ Have A Short Break For 15 _ 20 Minutes To Relax ♦ Visit Hoa Lu, Ancient Capital Of Vietnam Between 968 And 1010. You Have A Chance To Learn About Vietnamese History In The Feudal System Under Dinh, Le, And Ly Dynasty ♦ Visit Tam Coc By 1.5-hour Bamboo Boat. You Will Be Surprised By The Charming Beauty Here With Paddy Fields, River, Water, Cloud, Sky, And A Stunning Cave System During The Boat Trip. All Make A Masterpiece That The Vietnamese People Called Ha Long Bay On Land Continue The Tour For 45 Mins - Cycling Around The Village To Discover The Life Of The Local People. ♦ Get On Car To Return To Hanoi ♦ Get Dropped Off At Hotel In Hanoi ♦ Overnight In Hanoi
A9: Hanoi Airport - 100 KM 2 hours - Ninh Binh Tour (With Lunch) - Tam Coc - Hotel Drop | B9: ● FULL DAY – NINH BINH TOUR ♦ (100 KM 2 hours Drive) ♦ Arrive In Noi Bai International Airport. ♦ Get Picked Up By Our Friendly Driver Then Depart For Ninh Binh Province Have A Short Break For 15 _ 20 Minutes To Relax ♦ Visit Hoa Lu, Ancient Capital Of Vietnam Between 968 And 1010. You Have A Chance To Learn About Vietnamese History In The Feudal System Under Dinh, Le, And Ly Dynasty ♦ Have A Buffet Lunch In The Restaurant With A Lot Of Local Foods Such As Goat Meat, Fish, Chicken, And Fried Rice &Vegetarian Foods Are Always Available In The Buffet Lunch ♦ Visit Tam Coc By 1.5-hour Bamboo Boat. You Will Be Surprised By The Charming Beauty Here With Paddy Fields, River, Water, Cloud, Sky, And A Stunning Cave System During The Boat Trip. All Make A Masterpiece That The Vietnamese People Called Ha Long Bay On Land ♦ Continue The Tour For 45 Mins - Cycling Around The Village To Discover The Life Of The Local People. ♦ Get On Car To Return To Hanoi ♦ Get Dropped Off At Hotel In Hanoi ♦ Overnight In Hanoi
A10: Hanoi Hotel - 100 KM 2 hours - Ninh Binh Tour - Tam Coc - Hotel Drop | B10: ● FULL DAY – NINH BINH TOUR ♦ (100 KM 2 hours Drive) ♦ Get Picked Up By Our Friendly Driver Then Depart For Ninh Binh Province Have A Short Break For 15 _ 20 Minutes To Relax ♦ Visit Hoa Lu, Ancient Capital Of Vietnam Between 968 And 1010. You Have A Chance To Learn About Vietnamese History In The Feudal System Under Dinh, Le, And Ly Dynasty ♦ Visit Tam Coc By 1.5-hour Bamboo Boat. You Will Be Surprised By The Charming Beauty Here With Paddy Fields, River, Water, Cloud, Sky, And A Stunning Cave System During The Boat Trip. All Make A Masterpiece That The Vietnamese People Called Ha Long Bay On Land Continue The Tour For 45 Mins - Cycling Around The Village To Discover The Life Of The Local People. ♦ Get On Car To Return To Hanoi ♦ Get Dropped Off At Hotel In Hanoi ♦ Overnight In Hanoi
A11: Hanoi Hotel - 100 KM 2 hours - Ninh Binh Tour (With Lunch ) - Tam Coc - Hotel Drop | B11: ● FULL DAY – NINH BINH TOUR ♦ (100 KM 2 hours Drive) ♦ Get Picked Up By Our Friendly Driver Then Depart For Ninh Binh Province Have A Short Break For 15 _ 20 Minutes To Relax ♦ Visit Hoa Lu, Ancient Capital Of Vietnam Between 968 And 1010. You Have A Chance To Learn About Vietnamese History In The Feudal System Under Dinh, Le, And Ly Dynasty ♦ Have A Buffet Lunch In The Restaurant With A Lot Of Local Foods Such As Goat Meat, Fish, Chicken, And Fried Rice &Vegetarian Foods Are Always Available In The Buffet Lunch ♦ Visit Tam Coc By 1.5-hour Bamboo Boat. You Will Be Surprised By The Charming Beauty Here With Paddy Fields, River, Water, Cloud, Sky, And A Stunning Cave System During The Boat Trip. All Make A Masterpiece That The Vietnamese People Called Ha Long Bay On Land ♦ Continue The Tour For 45 Mins - Cycling Around The Village To Discover The Life Of The Local People. ♦ Get On Car To Return To Hanoi ♦ Get Dropped Off At Hotel In Hanoi ♦ Overnight In Hanoi
A12: Hanoi Airport - 200 Km 4 hours drive - Halong bay- 11:30 AM need to reach at Halong bay for cruise depart | B12: ● HANOI ARRIVAL - CRUISE WITH TI TOP & CAVE ROUTE– OVERNIGHT ON CRUISE ♦ Arrive Hanoi Airport Transfer To Ha Long Bay. Spending 3.5 Hours On Car To See How Beautiful Landscape Of Red River Delta. Upon Arrival At The Harbor, Meet Our Cruise Crew To Join The Fantastic Journey Around The New Seven Wonder On Luxury Cruise. Welcome And Check-in To Cruise, Your Lunch Will Be Served While The Boat Slowly Slides On Romantic Waves Of The Sea. Afternoon Is Time For Many Interesting Activities Such As: Visiting The Cave, Kayaking, Swimming, Sunbathing, Cooking Class. Enjoy Special Dinner Dish And Continuing Night Program With The Crew. ♦ Lunch And Dinner On Board. ♦ Overnight On Boat In Ha Long Bay. ♦ Please Note: The Program May Be Little Varied Upon The Cruise You Choose.
... A81: Phu Quoc Hotel - Phu Quoc Airport Drop | B81: ● PHU QUOC DEPARTURE ♦ Breakfast In Hotel ♦ Our Private Car Will Pick You Up From The Hotel And Drop You At Phu Quoc Airport.

Sheet Table 3
A1: Meeting Point
A3: AIRPORT | B3: INTERNATIONAL ARRIVAL | C3: DOMESTIC ARRIVAL
A4: HO CHI MINH | B4: ARRIVAL PILLAR - 10 GF | C4: ARRIVAL HALL- A1
A5: HANOI | B5: T2 - GATE A & GATE B | C5: T1 - GATE A,B,E
A6: DANANG | B6: GATE 5 | C6: GATE 5
A7: PHU QUOC | B7: Exit Gate | C7: Exit Gate
A9: Terms & Conditions | Advisory Notes
A10: Arrival Notes:
A11: ➢ On the starting day of Tour, Once client local vietnameese number received then WhatsApp group will be created by us, kindly use that for any further communication.
A12: ➢ Guest need to proceed to the Arrival Or Exit Gate & look for airport representative with guest name on Pla card.
A13: ➢ Customer need to wait for 10-15 minutes at the arrival gate once they meet our Airport Representative, Because car park at parking point.
A14: ➢ The maximum waiting period is 90 mins from time of flight landing.
A15: ➢ All Tours and Transfer max waiting period is 10 min SIC basis and 30 Min on PVT Basis.
A16: ➢ Guest need to take care of their belongings while leaving Hotel or Car, We will not be responsible for any belongings.
A18: Hotel Notes:
A19: ➢ Standard Check in Time: 02:00 Pm *Early check in is subject to hotel availability & hotel may charge directly to the guest.
A20: ➢ Standard Check out Time: 11:00 Am Late checkout subject to hotel availability & hotel may charge directly to the guest.
A21: ➢ Hotel may ask for SECURITY DEPOSIT up to 200 USD Or Passport depends on the hotels policy.
... A27: ➢ For Visit to Island, all guest are advised to carry extra pair of clothes, towel and slippers.

Sheet Table 3 (2)
A1: Travel Itinerary
B3: Meeting Point At Airport Arrival
B5: AIRPROT | C5: INTERNATIONAL ARRIVAL | D5: DOMESTIC ARRIVAL
B6: HO CHI MINH | C6: ARRIVAL - T2 - PILLAR 10 GF | D6: T1 - ARRIVAL - A1
B7: HANOI | C7: ARRIVAL - T2 - PILLAR 10 1F | D7: T1 - ARRIVAL - E2
B8: DANANG | C8: EXIT GATE PARKING | D8: T1 ARRIVAL PILLAR 4,5
B9: PHU QUOC | C9: EXIT GATE PARKING | D9: EXIT GATE PARKING
A11: Terms & Conditions | Advisory Notes
A12: Arrival Notes:
A13: ➢ On the starting day of Tour, Once client local vietnameese number received then WhatsApp group will be created by us, kindly use that for any further communication.
A14: ➢ Guest need to proceed to the Arrival Or Exit Gate & look for airport representative with guest name on Pla card.
A15: ➢ Customer need to wait for 10-15 minutes at the arrival gate once they meet our Airport Representative, Because car park at parking point.
A16: ➢ The maximum waiting period is 90 mins from time of flight landing.
A17: ➢ All Tours and Transfer max waiting period is 10 min SIC basis and 30 Min on PVT Basis.
A18: ➢ Guest need to take care of their belongings while leaving Hotel or Car, We will not be responsible for any belongings.
A20: Hotel Notes:
A21: ➢ Standard Check in Time: 02:00 Pm *Early check in is subject to hotel availability & hotel may charge directly to the guest.
A22: ➢ Standard Check out Time: 11:00 Am Late checkout subject to hotel availability & hotel may charge directly to the guest.
A23: ➢ Hotel may ask for SECURITY DEPOSIT up to 200 USD Or Passport depends on the hotels policy.
... A38: ➢ For any amendment requests in the Itinerary, the request shall be subject to possibilities.
